{
    "url": "https://en.wikipedia.org/wiki/Miguel_Alcubierre",
    "title": "Miguel Alcubierre",
    "html": "<!DOCTYPE html>\n<html class=\"client-nojs\" dir=\"ltr\" lang=\"en\">\n<head>\n<meta charset=\"utf-8\"/>\n<title>Miguel Alcubierre - Wikipedia</title>\n<script>document.documentElement.className=\"client-js\";RLCONF={\"wgBreakFrames\":false,\"wgSeparatorTransformTable\":[\"\",\"\"],\"wgDigitTransformTable\":[\"\",\"\"],\"wgDefaultDateFormat\":\"dmy\",\"wgMonthNames\":[\"\",\"January\",\"February\",\"March\",\"April\",\"May\",\"June\",\"July\",\"August\",\"September\",\"October\",\"November\",\"December\"],\"wgRequestId\":\"06c67eb5-2e18-4691-a6a0-0ea79396a93d\",\"wgCSPNonce\":false,\"wgCanonicalNamespace\":\"\",\"wgCanonicalSpecialPageName\":false,\"wgNamespaceNumber\":0,\"wgPageName\":\"Miguel_Alcubierre\",\"wgTitle\":\"Miguel Alcubierre\",\"wgCurRevisionId\":1077952888,\"wgRevisionId\":1077952888,\"wgArticleId\":1513690,\"wgIsArticle\":true,\"wgIsRedirect\":false,\"wgAction\":\"view\",\"wgUserName\":null,\"wgUserGroups\":[\"*\"],\"wgCategories\":[\"Webarchive template wayback links\",\"CS1 Spanish-language sources (es)\",\"Articles with short description\",\"Short description matches Wikidata\",\"Articles with hCards\",\"Commons category link is on Wikidata\",\"Articles with ISNI identifiers\",\"Articles with VIAF identifiers\",\n\"Articles with WORLDCATID identifiers\",\"Articles with BNF identifiers\",\"Articles with J9U identifiers\",\"Articles with LCCN identifiers\",\"Articles with NTA identifiers\",\"Articles with SUDOC identifiers\",\"1964 births\",\"Living people\",\"21st-century Mexican physicists\",\"Mexican nuclear physicists\",\"Scientists from Mexico City\",\"National Autonomous University of Mexico alumni\",\"National Autonomous University of Mexico faculty\",\"Alumni of Cardiff University\",\"Theoretical physicists\"],\"wgPageContentLanguage\":\"en\",\"wgPageContentModel\":\"wikitext\",\"wgRelevantPageName\":\"Miguel_Alcubierre\",\"wgRelevantArticleId\":1513690,\"wgIsProbablyEditable\":true,\"wgRelevantPageIsProbablyEditable\":true,\"wgRestrictionEdit\":[],\"wgRestrictionMove\":[],\"wgFlaggedRevsParams\":{\"tags\":{\"status\":{\"levels\":1}}},\"wgVisualEditor\":{\"pageLanguageCode\":\"en\",\"pageLanguageDir\":\"ltr\",\"pageVariantFallbacks\":\"en\"},\"wgMFDisplayWikibaseDescriptions\":{\"search\":true,\"watchlist\":true,\"tagline\":false,\"nearby\":true},\n\"wgWMESchemaEditAttemptStepOversample\":false,\"wgWMEPageLength\":10000,\"wgNoticeProject\":\"wikipedia\",\"wgVector2022PreviewPages\":[],\"wgMediaViewerOnClick\":true,\"wgMediaViewerEnabledByDefault\":true,\"wgPopupsFlags\":10,\"wgULSCurrentAutonym\":\"English\",\"wgEditSubmitButtonLabelPublish\":true,\"wgCentralAuthMobileDomain\":false,\"wgULSPosition\":\"interlanguage\",\"wgULSisCompactLinksEnabled\":true,\"wgWikibaseItemId\":\"Q2056796\",\"GEHomepageSuggestedEditsEnableTopics\":true,\"wgGETopicsMatchModeEnabled\":false,\"wgGEStructuredTaskRejectionReasonTextInputEnabled\":false};RLSTATE={\"ext.globalCssJs.user.styles\":\"ready\",\"site.styles\":\"ready\",\"user.styles\":\"ready\",\"ext.globalCssJs.user\":\"ready\",\"user\":\"ready\",\"user.options\":\"loading\",\"ext.cite.styles\":\"ready\",\"skins.vector.styles.legacy\":\"ready\",\"jquery.makeCollapsible.styles\":\"ready\",\"ext.visualEditor.desktopArticleTarget.noscript\":\"ready\",\"ext.wikimediaBadges\":\"ready\",\"ext.uls.interlanguage\":\"ready\",\"wikibase.client.init\":\"ready\"};RLPAGEMODULES=[\n\"ext.cite.ux-enhancements\",\"site\",\"mediawiki.page.ready\",\"jquery.makeCollapsible\",\"mediawiki.toc\",\"skins.vector.legacy.js\",\"mmv.head\",\"mmv.bootstrap.autostart\",\"ext.visualEditor.desktopArticleTarget.init\",\"ext.visualEditor.targetLoader\",\"ext.eventLogging\",\"ext.wikimediaEvents\",\"ext.navigationTiming\",\"ext.cx.eventlogging.campaigns\",\"ext.centralNotice.geoIP\",\"ext.centralNotice.startUp\",\"ext.gadget.ReferenceTooltips\",\"ext.gadget.charinsert\",\"ext.gadget.extra-toolbar-buttons\",\"ext.gadget.switcher\",\"ext.centralauth.centralautologin\",\"ext.popups\",\"ext.uls.compactlinks\",\"ext.uls.interface\",\"ext.growthExperiments.SuggestedEditSession\"];</script>\n<script>(RLQ=window.RLQ||[]).push(function(){mw.loader.implement(\"user.options@12s5i\",function($,jQuery,require,module){mw.user.tokens.set({\"patrolToken\":\"+\\\\\",\"watchToken\":\"+\\\\\",\"csrfToken\":\"+\\\\\"});});});</script>\n<link href=\"/w/load.php?lang=en&amp;modules=ext.cite.styles%7Cext.uls.interlanguage%7Cext.visualEditor.desktopArticleTarget.noscript%7Cext.wikimediaBadges%7Cjquery.makeCollapsible.styles%7Cskins.vector.styles.legacy%7Cwikibase.client.init&amp;only=styles&amp;skin=vector\" rel=\"stylesheet\"/>\n<script async=\"\" src=\"/w/load.php?lang=en&amp;modules=startup&amp;only=scripts&amp;raw=1&amp;skin=vector\"></script>\n<meta content=\"\" name=\"ResourceLoaderDynamicStyles\"/>\n<link href=\"/w/load.php?lang=en&amp;modules=site.styles&amp;only=styles&amp;skin=vector\" rel=\"stylesheet\"/>\n<meta content=\"MediaWiki 1.40.0-wmf.8\" name=\"generator\"/>\n<meta content=\"origin\" name=\"referrer\"/>\n<meta content=\"origin-when-crossorigin\" name=\"referrer\"/>\n<meta content=\"origin-when-cross-origin\" name=\"referrer\"/>\n<meta content=\"max-image-preview:standard\" name=\"robots\"/>\n<meta content=\"telephone=no\" name=\"format-detection\"/>\n<meta content=\"https://upload.wikimedia.org/wikipedia/commons/f/f8/Miguel_Alcubierre%E2%80%A201.jpg\" property=\"og:image\"/>\n<meta content=\"1200\" property=\"og:image:width\"/>\n<meta content=\"1303\" property=\"og:image:height\"/>\n<meta content=\"https://upload.wikimedia.org/wikipedia/commons/f/f8/Miguel_Alcubierre%E2%80%A201.jpg\" property=\"og:image\"/>\n<meta content=\"800\" property=\"og:image:width\"/>\n<meta content=\"869\" property=\"og:image:height\"/>\n<meta content=\"640\" property=\"og:image:width\"/>\n<meta content=\"695\" property=\"og:image:height\"/>\n<meta content=\"width=1000\" name=\"viewport\"/>\n<meta content=\"Miguel Alcubierre - Wikipedia\" property=\"og:title\"/>\n<meta content=\"website\" property=\"og:type\"/>\n<link href=\"//upload.wikimedia.org\" rel=\"preconnect\"/>\n<link href=\"//en.m.wikipedia.org/wiki/Miguel_Alcubierre\" media=\"only screen and (max-width: 720px)\" rel=\"alternate\"/>\n<link href=\"/w/index.php?title=Miguel_Alcubierre&amp;action=edit\" rel=\"alternate\" title=\"Edit this page\" type=\"application/x-wiki\"/>\n<link href=\"/static/apple-touch/wikipedia.png\" rel=\"apple-touch-icon\"/>\n<link href=\"/static/favicon/wikipedia.ico\" rel=\"icon\"/>\n<link href=\"/w/opensearch_desc.php\" rel=\"search\" title=\"Wikipedia (en)\" type=\"application/opensearchdescription+xml\"/>\n<link href=\"//en.wikipedia.org/w/api.php?action=rsd\" rel=\"EditURI\" type=\"application/rsd+xml\"/>\n<link href=\"https://creativecommons.org/licenses/by-sa/3.0/\" rel=\"license\"/>\n<link href=\"https://en.wikipedia.org/wiki/Miguel_Alcubierre\" rel=\"canonical\"/>\n<link href=\"//meta.wikimedia.org\" rel=\"dns-prefetch\"/>\n<link href=\"//login.wikimedia.org\" rel=\"dns-prefetch\"/>\n</head>\n<body class=\"skin-vector-legacy mediawiki ltr sitedir-ltr mw-hide-empty-elt ns-0 ns-subject mw-editable page-Miguel_Alcubierre rootpage-Miguel_Alcubierre skin-vector action-view vector-feature-language-in-header-enabled vector-feature-language-in-main-page-header-disabled vector-feature-language-alert-in-sidebar-enabled vector-feature-sticky-header-disabled vector-feature-sticky-header-edit-disabled vector-feature-table-of-contents-legacy-toc-disabled vector-feature-visual-enhancement-next-disabled vector-feature-page-tools-disabled vector-feature-limited-width-enabled vector-feature-limited-width-content-enabled\"><div class=\"noprint\" id=\"mw-page-base\"></div>\n<div class=\"noprint\" id=\"mw-head-base\"></div>\n<div class=\"mw-body\" id=\"content\" role=\"main\">\n<a id=\"top\"></a>\n<div id=\"siteNotice\"><!-- CentralNotice --><!--esi <esi:include src=\"/esitest-fa8a495983347898/content\" /> --> </div>\n<div class=\"mw-indicators\">\n</div>\n<h1 class=\"firstHeading mw-first-heading\" id=\"firstHeading\"><span class=\"mw-page-title-main\">Miguel Alcubierre</span></h1>\n<div class=\"vector-body\" id=\"bodyContent\">\n<div class=\"noprint\" id=\"siteSub\">From Wikipedia, the free encyclopedia</div>\n<div id=\"contentSub\"></div>\n<div id=\"contentSub2\"></div>\n<div id=\"jump-to-nav\"></div>\n<a class=\"mw-jump-link\" href=\"#mw-head\">Jump to navigation</a>\n<a class=\"mw-jump-link\" href=\"#searchInput\">Jump to search</a>\n<div class=\"mw-body-content mw-content-ltr\" dir=\"ltr\" id=\"mw-content-text\" lang=\"en\"><div class=\"mw-parser-output\"><div class=\"shortdescription nomobile noexcerpt noprint searchaux\" style=\"display:none\">Mexican theoretical physicist (born 1964)</div>\n<style data-mw-deduplicate=\"TemplateStyles:r1033289096\">.mw-parser-output .hatnote{font-style:italic}.mw-parser-output div.hatnote{padding-left:1.6em;margin-bottom:0.5em}.mw-parser-output .hatnote i{font-style:normal}.mw-parser-output .hatnote+link+.hatnote{margin-top:-0.5em}</style><div class=\"hatnote navigation-not-searchable\" role=\"note\">In this <a class=\"mw-redirect\" href=\"/wiki/Spanish_name\" title=\"Spanish name\">Spanish name</a>, the first or paternal <a href=\"/wiki/Surname\" title=\"Surname\">surname</a> is <i> Alcubierre</i> and the second or maternal family name is <i> Moya</i>.</div>\n<style data-mw-deduplicate=\"TemplateStyles:r1066479718\">.mw-parser-output .infobox-subbox{padding:0;border:none;margin:-3px;width:auto;min-width:100%;font-size:100%;clear:none;float:none;background-color:transparent}.mw-parser-output .infobox-3cols-child{margin:auto}.mw-parser-output .infobox .navbar{font-size:100%}body.skin-minerva .mw-parser-output .infobox-header,body.skin-minerva .mw-parser-output .infobox-subheader,body.skin-minerva .mw-parser-output .infobox-above,body.skin-minerva .mw-parser-output .infobox-title,body.skin-minerva .mw-parser-output .infobox-image,body.skin-minerva .mw-parser-output .infobox-full-data,body.skin-minerva .mw-parser-output .infobox-below{text-align:center}</style><table class=\"infobox biography vcard\"><tbody><tr><th class=\"infobox-above\" colspan=\"2\" style=\"font-size:125%;\"><div class=\"fn\" style=\"display:inline\">Miguel Alcubierre</div></th></tr><tr><td class=\"infobox-image\" colspan=\"2\"><a class=\"image\" href=\"/wiki/File:Miguel_Alcubierre%E2%80%A201.jpg\"><img alt=\"Miguel Alcubierre•01.jpg\" data-file-height=\"189\" data-file-width=\"174\" decoding=\"async\" height=\"189\" src=\"//upload.wikimedia.org/wikipedia/commons/f/f8/Miguel_Alcubierre%E2%80%A201.jpg\" width=\"174\"/></a><div class=\"infobox-caption\">Alcubierre in 2013.</div></td></tr><tr><th class=\"infobox-label\" scope=\"row\">Born</th><td class=\"infobox-data\"><div class=\"nickname\" style=\"display:inline\">Miguel Alcubierre Moya</div><br/><span style=\"display:none\"> (<span class=\"bday\">1964-03-28</span>) </span>March 28, 1964<span class=\"noprint ForceAgeToShow\"> (age 58)</span><br/><div class=\"birthplace\" style=\"display:inline\"><a href=\"/wiki/Mexico_City\" title=\"Mexico City\">Mexico City</a></div></td></tr><tr><th class=\"infobox-label\" scope=\"row\">Nationality</th><td class=\"infobox-data category\">Mexican</td></tr><tr><th class=\"infobox-label\" scope=\"row\">Alma mater</th><td class=\"infobox-data\"><a href=\"/wiki/National_Autonomous_University_of_Mexico\" title=\"National Autonomous University of Mexico\">National Autonomous University of Mexico</a> (Licentiate, MSc)<br/><a href=\"/wiki/Cardiff_University\" title=\"Cardiff University\">Cardiff University</a> (PhD)</td></tr><tr><th class=\"infobox-label\" scope=\"row\">Occupation</th><td class=\"infobox-data role\">Theoretical and Computational physicist</td></tr><tr><th class=\"infobox-label\" scope=\"row\">Known for</th><td class=\"infobox-data\"><a href=\"/wiki/Alcubierre_drive\" title=\"Alcubierre drive\">Alcubierre warp drive</a></td></tr><tr><th class=\"infobox-label\" scope=\"row\">Awards</th><td class=\"infobox-data\"><a href=\"/wiki/Gabino_Barreda\" title=\"Gabino Barreda\">Gabino Barreda Medal</a><br/> Merit in Sciences Medal<sup class=\"reference\" id=\"cite_ref-1\"><a href=\"#cite_note-1\">[1]</a></sup> <br/> Quo-Discovery Mind<sup class=\"reference\" id=\"cite_ref-2\"><a href=\"#cite_note-2\">[2]</a></sup></td></tr><tr><td class=\"infobox-full-data\" colspan=\"2\"><link href=\"mw-data:TemplateStyles:r1066479718\" rel=\"mw-deduplicated-inline-style\"/><b>Scientific career</b></td></tr><tr><th class=\"infobox-label\" scope=\"row\">Institutions</th><td class=\"infobox-data\"><a href=\"/wiki/Max_Planck_Institute_for_Gravitational_Physics\" title=\"Max Planck Institute for Gravitational Physics\">Max Planck Institute for Gravitational Physics</a><br/><a href=\"/wiki/National_Autonomous_University_of_Mexico\" title=\"National Autonomous University of Mexico\">National Autonomous University of Mexico</a></td></tr><tr><th class=\"infobox-label\" scope=\"row\"><a href=\"/wiki/Thesis\" title=\"Thesis\">Thesis</a></th><td class=\"infobox-data\"><i>Investigations in Numerical Relativity<sup class=\"reference\" id=\"cite_ref-3\"><a href=\"#cite_note-3\">[3]</a></sup></i> <span style=\"font-size:97%;\">(1988)</span></td></tr><tr><th class=\"infobox-label\" scope=\"row\"><a href=\"/wiki/Doctoral_advisor\" title=\"Doctoral advisor\">Doctoral advisor</a></th><td class=\"infobox-data\"><a href=\"/wiki/Bernard_F._Schutz\" title=\"Bernard F. Schutz\">Bernard F. Schutz</a></td></tr><tr style=\"display:none\"><td colspan=\"2\">\n</td></tr></tbody></table>\n<p><b>Miguel Alcubierre Moya</b> (born March 28, 1964) is a Mexican <a class=\"mw-redirect\" href=\"/wiki/Theoretical_physicist\" title=\"Theoretical physicist\">theoretical physicist</a>.<sup class=\"reference\" id=\"cite_ref-Cramer_1997_4-0\"><a href=\"#cite_note-Cramer_1997-4\">[4]</a></sup>\nAlcubierre is known for the proposed <a href=\"/wiki/Alcubierre_drive\" title=\"Alcubierre drive\">Alcubierre drive</a>, a speculative <a href=\"/wiki/Warp_drive\" title=\"Warp drive\">warp drive</a> by which a spacecraft could achieve faster-than-light travel.\n</p>\n<div aria-labelledby=\"mw-toc-heading\" class=\"toc\" id=\"toc\" role=\"navigation\"><input class=\"toctogglecheckbox\" id=\"toctogglecheckbox\" role=\"button\" style=\"display:none\" type=\"checkbox\"/><div class=\"toctitle\" dir=\"ltr\" lang=\"en\"><h2 id=\"mw-toc-heading\">Contents</h2><span class=\"toctogglespan\"><label class=\"toctogglelabel\" for=\"toctogglecheckbox\"></label></span></div>\n<ul>\n<li class=\"toclevel-1 tocsection-1\"><a href=\"#Personal_life\"><span class=\"tocnumber\">1</span> <span class=\"toctext\">Personal life</span></a></li>\n<li class=\"toclevel-1 tocsection-2\"><a href=\"#Academic_life\"><span class=\"tocnumber\">2</span> <span class=\"toctext\">Academic life</span></a></li>\n<li class=\"toclevel-1 tocsection-3\"><a href=\"#May_1994_paper\"><span class=\"tocnumber\">3</span> <span class=\"toctext\">May 1994 paper</span></a></li>\n<li class=\"toclevel-1 tocsection-4\"><a href=\"#Media_appearances\"><span class=\"tocnumber\">4</span> <span class=\"toctext\">Media appearances</span></a></li>\n<li class=\"toclevel-1 tocsection-5\"><a href=\"#Textbook\"><span class=\"tocnumber\">5</span> <span class=\"toctext\">Textbook</span></a></li>\n<li class=\"toclevel-1 tocsection-6\"><a href=\"#References\"><span class=\"tocnumber\">6</span> <span class=\"toctext\">References</span></a></li>\n</ul>\n</div>\n<h2><span class=\"mw-headline\" id=\"Personal_life\">Personal life</span><span class=\"mw-editsection\"><span class=\"mw-editsection-bracket\">[</span><a href=\"/w/index.php?title=Miguel_Alcubierre&amp;action=edit&amp;section=1\" title=\"Edit section: Personal life\">edit</a><span class=\"mw-editsection-bracket\">]</span></span></h2>\n<p>Alcubierre was born in Mexico City. His father, Miguel Alcubierre Ortiz, a <a href=\"/wiki/Spanish_Civil_War#Mexico\" title=\"Spanish Civil War\">Spanish refugee</a>, arrived in Mexico shortly after the <a href=\"/wiki/Spanish_Civil_War\" title=\"Spanish Civil War\">Spanish civil war</a> with his own father, Miguel Alcubierre Pérez.<sup class=\"reference\" id=\"cite_ref-5\"><a href=\"#cite_note-5\">[5]</a></sup> Alcubierre has three younger siblings, among them is historian Beatriz Alcubierre Moya.<sup class=\"reference\" id=\"cite_ref-6\"><a href=\"#cite_note-6\">[6]</a></sup>\n</p><p>From elementary throughout high school, Alcubierre attended <a href=\"/wiki/Colegio_Ciudad_de_M%C3%A9xico\" title=\"Colegio Ciudad de México\">Colegio Ciudad de México</a>. At the age of 13, his father bought him a small telescope, and, together with <a href=\"/wiki/Science_fiction\" title=\"Science fiction\">sci-fi</a> shows such as <i><a href=\"/wiki/Star_Trek\" title=\"Star Trek\">Star Trek</a></i>, motivated him to pursue a scientific career.<sup class=\"reference\" id=\"cite_ref-7\"><a href=\"#cite_note-7\">[7]</a></sup> At the age of 15, after having read <a href=\"/wiki/Patrick_Moore\" title=\"Patrick Moore\">Patrick Moore</a> and <a href=\"/wiki/David_A._Hardy\" title=\"David A. Hardy\">David Hardy</a>'s <i><a href=\"/wiki/David_A._Hardy#Major_books\" title=\"David A. Hardy\">Challenge of the Stars</a></i>, Alcubierre decided that he wanted to become an astronomer. He knew that in order to achieve this he would have to study <a href=\"/wiki/Physics\" title=\"Physics\">physics</a> first.<sup class=\"reference\" id=\"cite_ref-8\"><a href=\"#cite_note-8\">[8]</a></sup>\n</p>\n<h2><span class=\"mw-headline\" id=\"Academic_life\">Academic life</span><span class=\"mw-editsection\"><span class=\"mw-editsection-bracket\">[</span><a href=\"/w/index.php?title=Miguel_Alcubierre&amp;action=edit&amp;section=2\" title=\"Edit section: Academic life\">edit</a><span class=\"mw-editsection-bracket\">]</span></span></h2>\n<p>Alcubierre obtained a <a href=\"/wiki/Licentiate_(degree)\" title=\"Licentiate (degree)\">Licentiate</a> degree in <a href=\"/wiki/Physics\" title=\"Physics\">physics</a> in 1988 and a <a href=\"/wiki/Master_of_Science\" title=\"Master of Science\">MSc</a> degree in <a href=\"/wiki/Theoretical_physics\" title=\"Theoretical physics\">theoretical physics</a> in 1990, both at the <a href=\"/wiki/National_Autonomous_University_of_Mexico\" title=\"National Autonomous University of Mexico\">National Autonomous University of Mexico</a> (UNAM). At the end of 1990, Alcubierre moved to Wales to attend graduate school at <a href=\"/wiki/Cardiff_University\" title=\"Cardiff University\">Cardiff University</a>, receiving his <a href=\"/wiki/Doctor_of_Philosophy\" title=\"Doctor of Philosophy\">PhD</a> degree in 1994 through study of <a href=\"/wiki/Numerical_relativity\" title=\"Numerical relativity\">numerical general relativity</a>.<sup class=\"reference\" id=\"cite_ref-Cramer_1997_4-1\"><a href=\"#cite_note-Cramer_1997-4\">[4]</a></sup><sup class=\"reference\" id=\"cite_ref-Lifeboat_about_9-0\"><a href=\"#cite_note-Lifeboat_about-9\">[9]</a></sup><sup class=\"reference\" id=\"cite_ref-Lifeboat_Alcubierre-bio_10-0\"><a href=\"#cite_note-Lifeboat_Alcubierre-bio-10\">[10]</a></sup><sup class=\"reference\" id=\"cite_ref-11\"><a href=\"#cite_note-11\">[11]</a></sup>\nAfter 1996 he worked at the <a href=\"/wiki/Max_Planck_Institute_for_Gravitational_Physics\" title=\"Max Planck Institute for Gravitational Physics\">Max Planck Institute for Gravitational Physics</a> in <a href=\"/wiki/Potsdam\" title=\"Potsdam\">Potsdam</a>, Germany, developing new numerical techniques used in the description of <a href=\"/wiki/Black_hole\" title=\"Black hole\">black holes</a>.  Since 2002, he has worked at the Nuclear Sciences Institute of UNAM, where he conducts research in numerical relativity, employing computers to formulate and solve the physical equations first proposed by Albert Einstein.<sup class=\"reference\" id=\"cite_ref-career_12-0\"><a href=\"#cite_note-career-12\">[12]</a></sup> \nThe <a href=\"/wiki/Soliton\" title=\"Soliton\">solitary wave solutions</a> proposed  by Alcubierre for the <a href=\"/wiki/Einstein_field_equations\" title=\"Einstein field equations\">Einsteinian field equations</a> may possibly  prove general relativity consistent with the experimentally verified <a class=\"mw-redirect\" href=\"/wiki/Locality_principle\" title=\"Locality principle\">non-locality</a> of <a href=\"/wiki/Quantum_mechanics\" title=\"Quantum mechanics\">quantum mechanics</a>. This work militates against the idea that quantum non-locality would ultimately require abandoning the mathematical structure of <a href=\"/wiki/General_relativity\" title=\"General relativity\">general relativity</a>.\n</p><p>On June 11, 2012, Alcubierre was appointed Director of the Nuclear Sciences Institute at UNAM.\n</p><p>On June 14, 2016, the Governing Board of UNAM re-elected Alcubierre as Director of the Nuclear Sciences Institute for another four-year period.\n</p>\n<h2><span class=\"mw-headline\" id=\"May_1994_paper\">May 1994 paper</span><span class=\"mw-editsection\"><span class=\"mw-editsection-bracket\">[</span><a href=\"/w/index.php?title=Miguel_Alcubierre&amp;action=edit&amp;section=3\" title=\"Edit section: May 1994 paper\">edit</a><span class=\"mw-editsection-bracket\">]</span></span></h2>\n<p>Alcubierre is best known for the proposal of \"The Warp Drive: Hyper-fast travel within general relativity\" that was published in the science journal <i>Classical and Quantum Gravity</i>.<sup class=\"reference\" id=\"cite_ref-Warp_Alcubierre_13-0\"><a href=\"#cite_note-Warp_Alcubierre-13\">[13]</a></sup>  In this, he describes the <a href=\"/wiki/Alcubierre_drive\" title=\"Alcubierre drive\">Alcubierre drive</a>, a theoretical means of traveling <a href=\"/wiki/Faster-than-light\" title=\"Faster-than-light\">faster than light</a> that does not violate the physical principle that nothing can locally travel faster than light. In this paper,  he constructed a <a class=\"mw-redirect\" href=\"/wiki/Metric_(general_relativity)\" title=\"Metric (general relativity)\">model</a> that might transport a volume of flat space inside a \"bubble\" of curved space. This bubble, named as <i>Hyper-relativistic local-dynamic space,</i> is driven forward by a local expansion of space-time behind it, and an opposite contraction in front of it, so that theoretically a <a href=\"/wiki/Spacecraft\" title=\"Spacecraft\">spaceship</a> would be placed in motion by forces generated in the change made by <a class=\"mw-redirect\" href=\"/wiki/Space-time\" title=\"Space-time\">space-time</a>.\n</p>\n<h2><span class=\"mw-headline\" id=\"Media_appearances\">Media appearances</span><span class=\"mw-editsection\"><span class=\"mw-editsection-bracket\">[</span><a href=\"/w/index.php?title=Miguel_Alcubierre&amp;action=edit&amp;section=4\" title=\"Edit section: Media appearances\">edit</a><span class=\"mw-editsection-bracket\">]</span></span></h2>\n<p>Miguel Alcubierre made a special appearance on the TV productions <i><a href=\"/wiki/How_William_Shatner_Changed_the_World\" title=\"How William Shatner Changed the World\">How William Shatner Changed the World</a></i><sup class=\"reference\" id=\"cite_ref-IMDB_Alcubierre_14-0\"><a href=\"#cite_note-IMDB_Alcubierre-14\">[14]</a></sup>\nand <a href=\"/wiki/Michio_Kaku\" title=\"Michio Kaku\">Michio Kaku</a>'s <i><a href=\"/wiki/Sci_Fi_Science:_Physics_of_the_Impossible\" title=\"Sci Fi Science: Physics of the Impossible\">Sci Fi Science: Physics of the Impossible</a></i>,<sup class=\"reference\" id=\"cite_ref-IMDB_Sci-Fi-Science_15-0\"><a href=\"#cite_note-IMDB_Sci-Fi-Science-15\">[15]</a></sup><sup class=\"reference\" id=\"cite_ref-Nerds_review_16-0\"><a href=\"#cite_note-Nerds_review-16\">[16]</a></sup>\nin which his warp bubble theory was discussed.\n</p><p>Alcubierre has been invited twice to interviews on radio station <a class=\"mw-redirect\" href=\"/wiki/XEEP-AM\" title=\"XEEP-AM\">Radio Educación XEEP</a> (1060 AM), first on February 18, 2011, and later on March 4th 2011, on the technology-related talk show <i>Interfase</i>, where he explained his views on the current state of scientific and technology research in Mexico, and gave a brief introduction to his warp drive model and how it came to be.<sup class=\"reference\" id=\"cite_ref-radio-edu-1_17-0\"><a href=\"#cite_note-radio-edu-1-17\">[17]</a></sup><sup class=\"reference\" id=\"cite_ref-radio-edu-2_18-0\"><a href=\"#cite_note-radio-edu-2-18\">[18]</a></sup>\n</p>\n<h2><span class=\"mw-headline\" id=\"Textbook\">Textbook</span><span class=\"mw-editsection\"><span class=\"mw-editsection-bracket\">[</span><a href=\"/w/index.php?title=Miguel_Alcubierre&amp;action=edit&amp;section=5\" title=\"Edit section: Textbook\">edit</a><span class=\"mw-editsection-bracket\">]</span></span></h2>\n<p><i>Introduction to 3+1 Numerical Relativity</i> (International Series of Monographs on Physics, Paperback, 2012, <style data-mw-deduplicate=\"TemplateStyles:r1067248974\">.mw-parser-output cite.citation{font-style:inherit;word-wrap:break-word}.mw-parser-output .citation q{quotes:\"\\\"\"\"\\\"\"\"'\"\"'\"}.mw-parser-output .citation:target{background-color:rgba(0,127,255,0.133)}.mw-parser-output .id-lock-free a,.mw-parser-output .citation .cs1-lock-free a{background:linear-gradient(transparent,transparent),url(\"//upload.wikimedia.org/wikipedia/commons/6/65/Lock-green.svg\")right 0.1em center/9px no-repeat}.mw-parser-output .id-lock-limited a,.mw-parser-output .id-lock-registration a,.mw-parser-output .citation .cs1-lock-limited a,.mw-parser-output .citation .cs1-lock-registration a{background:linear-gradient(transparent,transparent),url(\"//upload.wikimedia.org/wikipedia/commons/d/d6/Lock-gray-alt-2.svg\")right 0.1em center/9px no-repeat}.mw-parser-output .id-lock-subscription a,.mw-parser-output .citation .cs1-lock-subscription a{background:linear-gradient(transparent,transparent),url(\"//upload.wikimedia.org/wikipedia/commons/a/aa/Lock-red-alt-2.svg\")right 0.1em center/9px no-repeat}.mw-parser-output .cs1-ws-icon a{background:linear-gradient(transparent,transparent),url(\"//upload.wikimedia.org/wikipedia/commons/4/4c/Wikisource-logo.svg\")right 0.1em center/12px no-repeat}.mw-parser-output .cs1-code{color:inherit;background:inherit;border:none;padding:inherit}.mw-parser-output .cs1-hidden-error{display:none;color:#d33}.mw-parser-output .cs1-visible-error{color:#d33}.mw-parser-output .cs1-maint{display:none;color:#3a3;margin-left:0.3em}.mw-parser-output .cs1-format{font-size:95%}.mw-parser-output .cs1-kern-left{padding-left:0.2em}.mw-parser-output .cs1-kern-right{padding-right:0.2em}.mw-parser-output .citation .mw-selflink{font-weight:inherit}</style><a class=\"mw-redirect\" href=\"/wiki/ISBN_(identifier)\" title=\"ISBN (identifier)\">ISBN</a> <a href=\"/wiki/Special:BookSources/978-0199656158\" title=\"Special:BookSources/978-0199656158\">978-0199656158</a>)\n</p>\n<h2><span class=\"mw-headline\" id=\"References\">References</span><span class=\"mw-editsection\"><span class=\"mw-editsection-bracket\">[</span><a href=\"/w/index.php?title=Miguel_Alcubierre&amp;action=edit&amp;section=6\" title=\"Edit section: References\">edit</a><span class=\"mw-editsection-bracket\">]</span></span></h2>\n<style data-mw-deduplicate=\"TemplateStyles:r1097025294\">.mw-parser-output .side-box{margin:4px 0;box-sizing:border-box;border:1px solid #aaa;font-size:88%;line-height:1.25em;background-color:#f9f9f9}.mw-parser-output .side-box-abovebelow,.mw-parser-output .side-box-text{padding:0.25em 0.9em}.mw-parser-output .side-box-image{padding:2px 0 2px 0.9em;text-align:center}.mw-parser-output .side-box-imageright{padding:2px 0.9em 2px 0;text-align:center}@media(min-width:500px){.mw-parser-output .side-box-flex{display:flex;align-items:center}.mw-parser-output .side-box-text{flex:1}}@media(min-width:720px){.mw-parser-output .side-box{width:238px}.mw-parser-output .side-box-right{clear:right;float:right;margin-left:1em}.mw-parser-output .side-box-left{margin-right:1em}}</style><div class=\"side-box side-box-right plainlinks sistersitebox\">\n<div class=\"side-box-flex\">\n<div class=\"side-box-image\"><img alt=\"\" class=\"noviewer\" data-file-height=\"1376\" data-file-width=\"1024\" decoding=\"async\" height=\"40\" src=\"//upload.wikimedia.org/wikipedia/en/thumb/4/4a/Commons-logo.svg/30px-Commons-logo.svg.png\" srcset=\"//upload.wikimedia.org/wikipedia/en/thumb/4/4a/Commons-logo.svg/45px-Commons-logo.svg.png 1.5x, //upload.wikimedia.org/wikipedia/en/thumb/4/4a/Commons-logo.svg/59px-Commons-logo.svg.png 2x\" width=\"30\"/></div>\n<div class=\"side-box-text plainlist\">Wikimedia Commons has media related to <span style=\"font-weight: bold; font-style: italic;\"><a class=\"extiw\" href=\"https://commons.wikimedia.org/wiki/Category:Miguel_Alcubierre\" title=\"commons:Category:Miguel Alcubierre\">Miguel Alcubierre</a></span>.</div></div>\n</div>\n<style data-mw-deduplicate=\"TemplateStyles:r1011085734\">.mw-parser-output .reflist{font-size:90%;margin-bottom:0.5em;list-style-type:decimal}.mw-parser-output .reflist .references{font-size:100%;margin-bottom:0;list-style-type:inherit}.mw-parser-output .reflist-columns-2{column-width:30em}.mw-parser-output .reflist-columns-3{column-width:25em}.mw-parser-output .reflist-columns{margin-top:0.3em}.mw-parser-output .reflist-columns ol{margin-top:0}.mw-parser-output .reflist-columns li{page-break-inside:avoid;break-inside:avoid-column}.mw-parser-output .reflist-upper-alpha{list-style-type:upper-alpha}.mw-parser-output .reflist-upper-roman{list-style-type:upper-roman}.mw-parser-output .reflist-lower-alpha{list-style-type:lower-alpha}.mw-parser-output .reflist-lower-greek{list-style-type:lower-greek}.mw-parser-output .reflist-lower-roman{list-style-type:lower-roman}</style><div class=\"reflist\">\n<div class=\"mw-references-wrap mw-references-columns\"><ol class=\"references\">\n<li id=\"cite_note-1\"><span class=\"mw-cite-backlink\"><b><a href=\"#cite_ref-1\">^</a></b></span> <span class=\"reference-text\"><link href=\"mw-data:TemplateStyles:r1067248974\" rel=\"mw-deduplicated-inline-style\"/><cite class=\"citation web cs1\"><a class=\"external text\" href=\"http://www.aldf.gob.mx/comsoc-comision-ciencia-y-tecnologia-aprueba-otorgar-medalla-al-merito-ciencias-y-artes-miguel-alcubierre-moya-carlos-artemio-coello-y-narro-robles-unam--5855.html\" rel=\"nofollow\">\".:: Comisión de Ciencia y Tecnología Aprueba Otorgar Medalla al Mérito en Ciencias y Artes a Miguel Alcubierre Moya, Carlos Artemio Coello y Narro Robles de la Unam ::\"</a>.</cite><span class=\"Z3988\" title=\"ctx_ver=Z39.88-2004&amp;rft_val_fmt=info%3Aofi%2Ffmt%3Akev%3Amtx%3Abook&amp;rft.genre=unknown&amp;rft.btitle=.%3A%3A+Comisi%C3%B3n+de+Ciencia+y+Tecnolog%C3%ADa+Aprueba+Otorgar+Medalla+al+M%C3%A9rito+en+Ciencias+y+Artes+a+Miguel+Alcubierre+Moya%2C+Carlos+Artemio+Coello+y+Narro+Robles+de+la+Unam+%3A%3A&amp;rft_id=http%3A%2F%2Fwww.aldf.gob.mx%2Fcomsoc-comision-ciencia-y-tecnologia-aprueba-otorgar-medalla-al-merito-ciencias-y-artes-miguel-alcubierre-moya-carlos-artemio-coello-y-narro-robles-unam--5855.html&amp;rfr_id=info%3Asid%2Fen.wikipedia.org%3AMiguel+Alcubierre\"></span></span>\n</li>\n<li id=\"cite_note-2\"><span class=\"mw-cite-backlink\"><b><a href=\"#cite_ref-2\">^</a></b></span> <span class=\"reference-text\"><link href=\"mw-data:TemplateStyles:r1067248974\" rel=\"mw-deduplicated-inline-style\"/><cite class=\"citation web cs1\"><a class=\"external text\" href=\"https://web.archive.org/web/20170810053419/http://www.grandesmaestros.unam.mx/dr-miguel-alcubierre\" rel=\"nofollow\">\"Grandes Maestros.UNAM » Dr. Miguel Alcubierre\"</a>. Archived from <a class=\"external text\" href=\"http://www.grandesmaestros.unam.mx/dr-miguel-alcubierre/\" rel=\"nofollow\">the original</a> on 2017-08-10.</cite><span class=\"Z3988\" title=\"ctx_ver=Z39.88-2004&amp;rft_val_fmt=info%3Aofi%2Ffmt%3Akev%3Amtx%3Abook&amp;rft.genre=unknown&amp;rft.btitle=Grandes+Maestros.UNAM+%C2%BB+Dr.+Miguel+Alcubierre&amp;rft_id=http%3A%2F%2Fwww.grandesmaestros.unam.mx%2Fdr-miguel-alcubierre%2F&amp;rfr_id=info%3Asid%2Fen.wikipedia.org%3AMiguel+Alcubierre\"></span></span>\n</li>\n<li id=\"cite_note-3\"><span class=\"mw-cite-backlink\"><b><a href=\"#cite_ref-3\">^</a></b></span> <span class=\"reference-text\"><a class=\"external text\" href=\"http://docplayer.es/73164018-Curriculum-vitae-dr-miguel-alcubierre-moya-fecha-de-actualizacion-mayo-2016-datos-personales.html\" rel=\"nofollow\">Miguel Alcubierre Curriculum vitae</a></span>\n</li>\n<li id=\"cite_note-Cramer_1997-4\"><span class=\"mw-cite-backlink\">^ <a href=\"#cite_ref-Cramer_1997_4-0\"><sup><i><b>a</b></i></sup></a> <a href=\"#cite_ref-Cramer_1997_4-1\"><sup><i><b>b</b></i></sup></a></span> <span class=\"reference-text\"><link href=\"mw-data:TemplateStyles:r1067248974\" rel=\"mw-deduplicated-inline-style\"/><cite class=\"citation web cs1\" id=\"CITEREFCramer1996\"><a href=\"/wiki/John_G._Cramer\" title=\"John G. Cramer\">Cramer, John G.</a> (November 1996). <a class=\"external text\" href=\"http://www.npl.washington.edu/AV/altvw81.html\" rel=\"nofollow\">\"Alternate View: The Alcubierre Warp Drive\"</a>. <i><a href=\"/wiki/Analog_Science_Fiction_and_Fact\" title=\"Analog Science Fiction and Fact\">Analog Science Fiction and Fact</a></i>. <a href=\"/wiki/Penny_Publications\" title=\"Penny Publications\">Penny Publications</a><span class=\"reference-accessdate\">. Retrieved <span class=\"nowrap\">22 September</span> 2012</span>.</cite><span class=\"Z3988\" title=\"ctx_ver=Z39.88-2004&amp;rft_val_fmt=info%3Aofi%2Ffmt%3Akev%3Amtx%3Ajournal&amp;rft.genre=unknown&amp;rft.jtitle=Analog+Science+Fiction+and+Fact&amp;rft.atitle=Alternate+View%3A+The+Alcubierre+Warp+Drive&amp;rft.date=1996-11&amp;rft.aulast=Cramer&amp;rft.aufirst=John+G.&amp;rft_id=http%3A%2F%2Fwww.npl.washington.edu%2FAV%2Faltvw81.html&amp;rfr_id=info%3Asid%2Fen.wikipedia.org%3AMiguel+Alcubierre\"></span></span>\n</li>\n<li id=\"cite_note-5\"><span class=\"mw-cite-backlink\"><b><a href=\"#cite_ref-5\">^</a></b></span> <span class=\"reference-text\"><link href=\"mw-data:TemplateStyles:r1067248974\" rel=\"mw-deduplicated-inline-style\"/><cite class=\"citation web cs1\"><a class=\"external text\" href=\"https://www.heraldo.es/noticias/ocio-cultura/2009/04/28/las-siete-vidas-miguel-alcubierre-46212-1361024.html\" rel=\"nofollow\">\"Las siete vidas de Miguel Alcubierre\"</a>.</cite><span class=\"Z3988\" title=\"ctx_ver=Z39.88-2004&amp;rft_val_fmt=info%3Aofi%2Ffmt%3Akev%3Amtx%3Abook&amp;rft.genre=unknown&amp;rft.btitle=Las+siete+vidas+de+Miguel+Alcubierre&amp;rft_id=https%3A%2F%2Fwww.heraldo.es%2Fnoticias%2Focio-cultura%2F2009%2F04%2F28%2Flas-siete-vidas-miguel-alcubierre-46212-1361024.html&amp;rfr_id=info%3Asid%2Fen.wikipedia.org%3AMiguel+Alcubierre\"></span></span>\n</li>\n<li id=\"cite_note-6\"><span class=\"mw-cite-backlink\"><b><a href=\"#cite_ref-6\">^</a></b></span> <span class=\"reference-text\"><link href=\"mw-data:TemplateStyles:r1067248974\" rel=\"mw-deduplicated-inline-style\"/><cite class=\"citation web cs1\"><a class=\"external text\" href=\"https://www.aacademica.org/beatriz.alcubierre\" rel=\"nofollow\">\"Beatriz Alcubierre Moya\"</a>.</cite><span class=\"Z3988\" title=\"ctx_ver=Z39.88-2004&amp;rft_val_fmt=info%3Aofi%2Ffmt%3Akev%3Amtx%3Abook&amp;rft.genre=unknown&amp;rft.btitle=Beatriz+Alcubierre+Moya&amp;rft_id=https%3A%2F%2Fwww.aacademica.org%2Fbeatriz.alcubierre&amp;rfr_id=info%3Asid%2Fen.wikipedia.org%3AMiguel+Alcubierre\"></span></span>\n</li>\n<li id=\"cite_note-7\"><span class=\"mw-cite-backlink\"><b><a href=\"#cite_ref-7\">^</a></b></span> <span class=\"reference-text\">Archived at <a class=\"external text\" href=\"https://ghostarchive.org/varchive/youtube/20211211/k78_F-cYIhQ\" rel=\"nofollow\">Ghostarchive</a> and the <a class=\"external text\" href=\"https://web.archive.org/web/20200219074817/https://www.youtube.com/watch?v=k78_F-cYIhQ\" rel=\"nofollow\">Wayback Machine</a>: <link href=\"mw-data:TemplateStyles:r1067248974\" rel=\"mw-deduplicated-inline-style\"/><cite class=\"citation audio-visual cs1\"><a class=\"external text\" href=\"https://www.youtube.com/watch?v=k78_F-cYIhQ&amp;t=24\" rel=\"nofollow\"><i>Ganándole a la velocidad de la luz | Miguel Alcubierre | CDI 2016 Play the Game</i></a>. <i><a href=\"/wiki/YouTube\" title=\"YouTube\">YouTube</a></i>.</cite><span class=\"Z3988\" title=\"ctx_ver=Z39.88-2004&amp;rft_val_fmt=info%3Aofi%2Ffmt%3Akev%3Amtx%3Abook&amp;rft.genre=unknown&amp;rft.btitle=Gan%C3%A1ndole+a+la+velocidad+de+la+luz+%7C+Miguel+Alcubierre+%7C+CDI+2016+Play+the+Game&amp;rft_id=https%3A%2F%2Fwww.youtube.com%2Fwatch%3Fv%3Dk78_F-cYIhQ%26t%3D24&amp;rfr_id=info%3Asid%2Fen.wikipedia.org%3AMiguel+Alcubierre\"></span></span>\n</li>\n<li id=\"cite_note-8\"><span class=\"mw-cite-backlink\"><b><a href=\"#cite_ref-8\">^</a></b></span> <span class=\"reference-text\"><link href=\"mw-data:TemplateStyles:r1067248974\" rel=\"mw-deduplicated-inline-style\"/><cite class=\"citation web cs1\"><a class=\"external text\" href=\"http://www.fundacionunam.org.mx/rostros/miguel-alcubierre-el-fisico-fanatico-de-la-ciencia-ficcion/\" rel=\"nofollow\">\"Miguel Alcubierre, el físico fanático de la ciencia ficción | Fundación UNAM\"</a>.</cite><span class=\"Z3988\" title=\"ctx_ver=Z39.88-2004&amp;rft_val_fmt=info%3Aofi%2Ffmt%3Akev%3Amtx%3Abook&amp;rft.genre=unknown&amp;rft.btitle=Miguel+Alcubierre%2C+el+f%C3%ADsico+fan%C3%A1tico+de+la+ciencia+ficci%C3%B3n+%26%23124%3B+Fundaci%C3%B3n+UNAM&amp;rft_id=http%3A%2F%2Fwww.fundacionunam.org.mx%2Frostros%2Fmiguel-alcubierre-el-fisico-fanatico-de-la-ciencia-ficcion%2F&amp;rfr_id=info%3Asid%2Fen.wikipedia.org%3AMiguel+Alcubierre\"></span></span>\n</li>\n<li id=\"cite_note-Lifeboat_about-9\"><span class=\"mw-cite-backlink\"><b><a href=\"#cite_ref-Lifeboat_about_9-0\">^</a></b></span> <span class=\"reference-text\"><link href=\"mw-data:TemplateStyles:r1067248974\" rel=\"mw-deduplicated-inline-style\"/><cite class=\"citation web cs1\"><a class=\"external text\" href=\"http://lifeboat.com/ex/about\" rel=\"nofollow\">\"About\"</a>. Lifeboat Foundation<span class=\"reference-accessdate\">. Retrieved <span class=\"nowrap\">22 September</span> 2012</span>.</cite><span class=\"Z3988\" title=\"ctx_ver=Z39.88-2004&amp;rft_val_fmt=info%3Aofi%2Ffmt%3Akev%3Amtx%3Abook&amp;rft.genre=unknown&amp;rft.btitle=About&amp;rft.pub=Lifeboat+Foundation&amp;rft_id=http%3A%2F%2Flifeboat.com%2Fex%2Fabout&amp;rfr_id=info%3Asid%2Fen.wikipedia.org%3AMiguel+Alcubierre\"></span></span>\n</li>\n<li id=\"cite_note-Lifeboat_Alcubierre-bio-10\"><span class=\"mw-cite-backlink\"><b><a href=\"#cite_ref-Lifeboat_Alcubierre-bio_10-0\">^</a></b></span> <span class=\"reference-text\"><link href=\"mw-data:TemplateStyles:r1067248974\" rel=\"mw-deduplicated-inline-style\"/><cite class=\"citation web cs1\"><a class=\"external text\" href=\"http://lifeboat.com/ex/bios.miguel.alcubierre\" rel=\"nofollow\">\"Advisory Board: Dr. Miguel Alcubierre\"</a>. Lifeboat Foundation<span class=\"reference-accessdate\">. Retrieved <span class=\"nowrap\">22 September</span> 2012</span>.</cite><span class=\"Z3988\" title=\"ctx_ver=Z39.88-2004&amp;rft_val_fmt=info%3Aofi%2Ffmt%3Akev%3Amtx%3Abook&amp;rft.genre=unknown&amp;rft.btitle=Advisory+Board%3A+Dr.+Miguel+Alcubierre&amp;rft.pub=Lifeboat+Foundation&amp;rft_id=http%3A%2F%2Flifeboat.com%2Fex%2Fbios.miguel.alcubierre&amp;rfr_id=info%3Asid%2Fen.wikipedia.org%3AMiguel+Alcubierre\"></span></span>\n</li>\n<li id=\"cite_note-11\"><span class=\"mw-cite-backlink\"><b><a href=\"#cite_ref-11\">^</a></b></span> <span class=\"reference-text\"><a class=\"external text\" href=\"http://www.nucleares.unam.mx/~soma/miembros/MAlcubierre.htm\" rel=\"nofollow\">Biography Miguel Alcubierre Moya</a> <a class=\"external text\" href=\"https://web.archive.org/web/20140429211320/http://www.nucleares.unam.mx/~soma/miembros/MAlcubierre.htm\" rel=\"nofollow\">Archived</a> 2014-04-29 at the <a href=\"/wiki/Wayback_Machine\" title=\"Wayback Machine\">Wayback Machine</a> - website of the Instituto de Ciencias Nucleares</span>\n</li>\n<li id=\"cite_note-career-12\"><span class=\"mw-cite-backlink\"><b><a href=\"#cite_ref-career_12-0\">^</a></b></span> <span class=\"reference-text\"><link href=\"mw-data:TemplateStyles:r1067248974\" rel=\"mw-deduplicated-inline-style\"/><cite class=\"citation web cs1 cs1-prop-foreign-lang-source\" id=\"CITEREFCansigno2008\">Cansigno, Rafael (aka \"sigloxiii\") (24 March 2008). <a class=\"external text\" href=\"https://web.archive.org/web/20120922190342/http://tenoch.scimexico.com/2008/03/24/cientificos-mexicanos-miguel-alcubierre-moya/\" rel=\"nofollow\">\"Mexican Scientists: Miguel Alcubierre Moya\"</a>. <i>Tenoch</i> (in Spanish). Archived from <a class=\"external text\" href=\"http://tenoch.scimexico.com/2008/03/24/cientificos-mexicanos-miguel-alcubierre-moya/\" rel=\"nofollow\">the original</a> <span class=\"cs1-format\">(<a href=\"/wiki/Blog\" title=\"Blog\">blog</a>)</span> on 22 September 2012<span class=\"reference-accessdate\">. Retrieved <span class=\"nowrap\">22 September</span> 2012</span>.</cite><span class=\"Z3988\" title=\"ctx_ver=Z39.88-2004&amp;rft_val_fmt=info%3Aofi%2Ffmt%3Akev%3Amtx%3Ajournal&amp;rft.genre=unknown&amp;rft.jtitle=Tenoch&amp;rft.atitle=Mexican+Scientists%3A+Miguel+Alcubierre+Moya&amp;rft.date=2008-03-24&amp;rft.aulast=Cansigno&amp;rft.aufirst=Rafael+%28aka+%22sigloxiii%22%29&amp;rft_id=http%3A%2F%2Ftenoch.scimexico.com%2F2008%2F03%2F24%2Fcientificos-mexicanos-miguel-alcubierre-moya%2F&amp;rfr_id=info%3Asid%2Fen.wikipedia.org%3AMiguel+Alcubierre\"></span></span>\n</li>\n<li id=\"cite_note-Warp_Alcubierre-13\"><span class=\"mw-cite-backlink\"><b><a href=\"#cite_ref-Warp_Alcubierre_13-0\">^</a></b></span> <span class=\"reference-text\"><link href=\"mw-data:TemplateStyles:r1067248974\" rel=\"mw-deduplicated-inline-style\"/><cite class=\"citation journal cs1\" id=\"CITEREFAlcubierre1994\">Alcubierre, Miguel (1994). \"The warp drive: hyper-fast travel within general relativity\". <i>Classical and Quantum Gravity</i>. <b>11</b> (5): L73–L77. <a class=\"mw-redirect\" href=\"/wiki/ArXiv_(identifier)\" title=\"ArXiv (identifier)\">arXiv</a>:<span class=\"cs1-lock-free\" title=\"Freely accessible\"><a class=\"external text\" href=\"//arxiv.org/abs/gr-qc/0009013\" rel=\"nofollow\">gr-qc/0009013</a></span>. <a class=\"mw-redirect\" href=\"/wiki/Bibcode_(identifier)\" title=\"Bibcode (identifier)\">Bibcode</a>:<a class=\"external text\" href=\"https://ui.adsabs.harvard.edu/abs/1994CQGra..11L..73A\" rel=\"nofollow\">1994CQGra..11L..73A</a>. <a class=\"mw-redirect\" href=\"/wiki/Doi_(identifier)\" title=\"Doi (identifier)\">doi</a>:<a class=\"external text\" href=\"https://doi.org/10.1088%2F0264-9381%2F11%2F5%2F001\" rel=\"nofollow\">10.1088/0264-9381/11/5/001</a>. <a class=\"mw-redirect\" href=\"/wiki/S2CID_(identifier)\" title=\"S2CID (identifier)\">S2CID</a> <a class=\"external text\" href=\"https://api.semanticscholar.org/CorpusID:4797900\" rel=\"nofollow\">4797900</a>.</cite><span class=\"Z3988\" title=\"ctx_ver=Z39.88-2004&amp;rft_val_fmt=info%3Aofi%2Ffmt%3Akev%3Amtx%3Ajournal&amp;rft.genre=article&amp;rft.jtitle=Classical+and+Quantum+Gravity&amp;rft.atitle=The+warp+drive%3A+hyper-fast+travel+within+general+relativity&amp;rft.volume=11&amp;rft.issue=5&amp;rft.pages=L73-L77&amp;rft.date=1994&amp;rft_id=info%3Aarxiv%2Fgr-qc%2F0009013&amp;rft_id=https%3A%2F%2Fapi.semanticscholar.org%2FCorpusID%3A4797900%23id-name%3DS2CID&amp;rft_id=info%3Adoi%2F10.1088%2F0264-9381%2F11%2F5%2F001&amp;rft_id=info%3Abibcode%2F1994CQGra..11L..73A&amp;rft.aulast=Alcubierre&amp;rft.aufirst=Miguel&amp;rfr_id=info%3Asid%2Fen.wikipedia.org%3AMiguel+Alcubierre\"></span></span>\n</li>\n<li id=\"cite_note-IMDB_Alcubierre-14\"><span class=\"mw-cite-backlink\"><b><a href=\"#cite_ref-IMDB_Alcubierre_14-0\">^</a></b></span> <span class=\"reference-text\"><link href=\"mw-data:TemplateStyles:r1067248974\" rel=\"mw-deduplicated-inline-style\"/><cite class=\"citation web cs1\"><a class=\"external text\" href=\"https://www.imdb.com/name/nm3824018/\" rel=\"nofollow\">\"Miguel Alcubierre\"</a>. <i><a class=\"mw-redirect\" href=\"/wiki/Internet_Movie_Database\" title=\"Internet Movie Database\">Internet Movie Database</a> (IMDb)</i><span class=\"reference-accessdate\">. Retrieved <span class=\"nowrap\">22 September</span> 2012</span>.</cite><span class=\"Z3988\" title=\"ctx_ver=Z39.88-2004&amp;rft_val_fmt=info%3Aofi%2Ffmt%3Akev%3Amtx%3Ajournal&amp;rft.genre=unknown&amp;rft.jtitle=Internet+Movie+Database+%28IMDb%29&amp;rft.atitle=Miguel+Alcubierre&amp;rft_id=https%3A%2F%2Fwww.imdb.com%2Fname%2Fnm3824018%2F&amp;rfr_id=info%3Asid%2Fen.wikipedia.org%3AMiguel+Alcubierre\"></span></span>\n</li>\n<li id=\"cite_note-IMDB_Sci-Fi-Science-15\"><span class=\"mw-cite-backlink\"><b><a href=\"#cite_ref-IMDB_Sci-Fi-Science_15-0\">^</a></b></span> <span class=\"reference-text\"><link href=\"mw-data:TemplateStyles:r1067248974\" rel=\"mw-deduplicated-inline-style\"/><cite class=\"citation web cs1\"><a class=\"external text\" href=\"https://www.imdb.com/title/tt1588120/\" rel=\"nofollow\">\"Sci Fi Science: Physics of the Impossible (2009)\"</a>. <i>IMDb</i><span class=\"reference-accessdate\">. Retrieved <span class=\"nowrap\">22 September</span> 2012</span>.</cite><span class=\"Z3988\" title=\"ctx_ver=Z39.88-2004&amp;rft_val_fmt=info%3Aofi%2Ffmt%3Akev%3Amtx%3Ajournal&amp;rft.genre=unknown&amp;rft.jtitle=IMDb&amp;rft.atitle=Sci+Fi+Science%3A+Physics+of+the+Impossible+%282009%29&amp;rft_id=https%3A%2F%2Fwww.imdb.com%2Ftitle%2Ftt1588120%2F&amp;rfr_id=info%3Asid%2Fen.wikipedia.org%3AMiguel+Alcubierre\"></span></span>\n</li>\n<li id=\"cite_note-Nerds_review-16\"><span class=\"mw-cite-backlink\"><b><a href=\"#cite_ref-Nerds_review_16-0\">^</a></b></span> <span class=\"reference-text\"><link href=\"mw-data:TemplateStyles:r1067248974\" rel=\"mw-deduplicated-inline-style\"/><cite class=\"citation web cs1\"><a class=\"external text\" href=\"http://nerdsontherocks.com/review-shooter-sci-fi-science-physics-of-the-impossible\" rel=\"nofollow\">\"Review Shooter: Sci Fi Science: Physics of the Impossible\"</a> <span class=\"cs1-format\">(blog)</span>. <i>NerdsOnTheRocks.com</i>. 19 November 2010.</cite><span class=\"Z3988\" title=\"ctx_ver=Z39.88-2004&amp;rft_val_fmt=info%3Aofi%2Ffmt%3Akev%3Amtx%3Ajournal&amp;rft.genre=unknown&amp;rft.jtitle=NerdsOnTheRocks.com&amp;rft.atitle=Review+Shooter%3A+Sci+Fi+Science%3A+Physics+of+the+Impossible&amp;rft.date=2010-11-19&amp;rft_id=http%3A%2F%2Fnerdsontherocks.com%2Freview-shooter-sci-fi-science-physics-of-the-impossible&amp;rfr_id=info%3Asid%2Fen.wikipedia.org%3AMiguel+Alcubierre\"></span></span>\n</li>\n<li id=\"cite_note-radio-edu-1-17\"><span class=\"mw-cite-backlink\"><b><a href=\"#cite_ref-radio-edu-1_17-0\">^</a></b></span> <span class=\"reference-text\"><link href=\"mw-data:TemplateStyles:r1067248974\" rel=\"mw-deduplicated-inline-style\"/><cite class=\"citation podcast cs1 cs1-prop-foreign-lang-source\"><a class=\"external text\" href=\"http://1060interfase.podomatic.com/player/web/2011-02-21T05_02_17-08_00\" rel=\"nofollow\">\"Interfase S3E07: Science and Technology in Mexico; Guest: Dr. Miguel Alcubierre (Part 1)\"</a>. <i>Podomatic.com</i> (Podcast) (in Spanish). 18 February 2011<span class=\"reference-accessdate\">. Retrieved <span class=\"nowrap\">22 September</span> 2012</span>.</cite><span class=\"Z3988\" title=\"ctx_ver=Z39.88-2004&amp;rft_val_fmt=info%3Aofi%2Ffmt%3Akev%3Amtx%3Abook&amp;rft.genre=unknown&amp;rft.btitle=Interfase+S3E07%3A+Science+and+Technology+in+Mexico%3B+Guest%3A+Dr.+Miguel+Alcubierre+%28Part+1%29&amp;rft.date=2011-02-18&amp;rft_id=http%3A%2F%2F1060interfase.podomatic.com%2Fplayer%2Fweb%2F2011-02-21T05_02_17-08_00&amp;rfr_id=info%3Asid%2Fen.wikipedia.org%3AMiguel+Alcubierre\"></span></span>\n</li>\n<li id=\"cite_note-radio-edu-2-18\"><span class=\"mw-cite-backlink\"><b><a href=\"#cite_ref-radio-edu-2_18-0\">^</a></b></span> <span class=\"reference-text\"><link href=\"mw-data:TemplateStyles:r1067248974\" rel=\"mw-deduplicated-inline-style\"/><cite class=\"citation podcast cs1 cs1-prop-foreign-lang-source\"><a class=\"external text\" href=\"http://1060interfase.podomatic.com/player/web/2011-03-07T06_37_10-08_00\" rel=\"nofollow\">\"Interfase S309: Science and Technology in Mexico; Guest: Dr. Miguel Alcubierre (Part 2)\"</a>. <i>Podomatic.com</i> (Podcast) (in Spanish). 4 March 2011<span class=\"reference-accessdate\">. Retrieved <span class=\"nowrap\">22 September</span> 2012</span>.</cite><span class=\"Z3988\" title=\"ctx_ver=Z39.88-2004&amp;rft_val_fmt=info%3Aofi%2Ffmt%3Akev%3Amtx%3Abook&amp;rft.genre=unknown&amp;rft.btitle=Interfase+S309%3A+Science+and+Technology+in+Mexico%3B+Guest%3A+Dr.+Miguel+Alcubierre+%28Part+2%29&amp;rft.date=2011-03-04&amp;rft_id=http%3A%2F%2F1060interfase.podomatic.com%2Fplayer%2Fweb%2F2011-03-07T06_37_10-08_00&amp;rfr_id=info%3Asid%2Fen.wikipedia.org%3AMiguel+Alcubierre\"></span></span>\n</li>\n</ol></div></div>\n<div class=\"navbox-styles nomobile\"><style data-mw-deduplicate=\"TemplateStyles:r1061467846\">.mw-parser-output .navbox{box-sizing:border-box;border:1px solid #a2a9b1;width:100%;clear:both;font-size:88%;text-align:center;padding:1px;margin:1em auto 0}.mw-parser-output .navbox .navbox{margin-top:0}.mw-parser-output .navbox+.navbox,.mw-parser-output .navbox+.navbox-styles+.navbox{margin-top:-1px}.mw-parser-output .navbox-inner,.mw-parser-output .navbox-subgroup{width:100%}.mw-parser-output .navbox-group,.mw-parser-output .navbox-title,.mw-parser-output .navbox-abovebelow{padding:0.25em 1em;line-height:1.5em;text-align:center}.mw-parser-output .navbox-group{white-space:nowrap;text-align:right}.mw-parser-output .navbox,.mw-parser-output .navbox-subgroup{background-color:#fdfdfd}.mw-parser-output .navbox-list{line-height:1.5em;border-color:#fdfdfd}.mw-parser-output .navbox-list-with-group{text-align:left;border-left-width:2px;border-left-style:solid}.mw-parser-output tr+tr>.navbox-abovebelow,.mw-parser-output tr+tr>.navbox-group,.mw-parser-output tr+tr>.navbox-image,.mw-parser-output tr+tr>.navbox-list{border-top:2px solid #fdfdfd}.mw-parser-output .navbox-title{background-color:#ccf}.mw-parser-output .navbox-abovebelow,.mw-parser-output .navbox-group,.mw-parser-output .navbox-subgroup .navbox-title{background-color:#ddf}.mw-parser-output .navbox-subgroup .navbox-group,.mw-parser-output .navbox-subgroup .navbox-abovebelow{background-color:#e6e6ff}.mw-parser-output .navbox-even{background-color:#f7f7f7}.mw-parser-output .navbox-odd{background-color:transparent}.mw-parser-output .navbox .hlist td dl,.mw-parser-output .navbox .hlist td ol,.mw-parser-output .navbox .hlist td ul,.mw-parser-output .navbox td.hlist dl,.mw-parser-output .navbox td.hlist ol,.mw-parser-output .navbox td.hlist ul{padding:0.125em 0}.mw-parser-output .navbox .navbar{display:block;font-size:100%}.mw-parser-output .navbox-title .navbar{float:left;text-align:left;margin-right:0.5em}</style></div><div aria-labelledby=\"Authority_control_frameless&amp;#124;text-top&amp;#124;10px&amp;#124;alt=Edit_this_at_Wikidata&amp;#124;link=https&amp;#58;//www.wikidata.org/wiki/Q2056796#identifiers&amp;#124;class=noprint&amp;#124;Edit_this_at_Wikidata\" class=\"navbox authority-control\" role=\"navigation\" style=\"padding:3px\"><table class=\"nowraplinks hlist mw-collapsible autocollapse navbox-inner\" style=\"border-spacing:0;background:transparent;color:inherit\"><tbody><tr><th class=\"navbox-title\" colspan=\"2\" scope=\"col\"><div id=\"Authority_control_frameless&amp;#124;text-top&amp;#124;10px&amp;#124;alt=Edit_this_at_Wikidata&amp;#124;link=https&amp;#58;//www.wikidata.org/wiki/Q2056796#identifiers&amp;#124;class=noprint&amp;#124;Edit_this_at_Wikidata\" style=\"font-size:114%;margin:0 4em\"><a href=\"/wiki/Help:Authority_control\" title=\"Help:Authority control\">Authority control</a> <a href=\"https://www.wikidata.org/wiki/Q2056796#identifiers\" title=\"Edit this at Wikidata\"><img alt=\"Edit this at Wikidata\" class=\"noprint\" data-file-height=\"20\" data-file-width=\"20\" decoding=\"async\" height=\"10\" src=\"//upload.wikimedia.org/wikipedia/en/thumb/8/8a/OOjs_UI_icon_edit-ltr-progressive.svg/10px-OOjs_UI_icon_edit-ltr-progressive.svg.png\" srcset=\"//upload.wikimedia.org/wikipedia/en/thumb/8/8a/OOjs_UI_icon_edit-ltr-progressive.svg/15px-OOjs_UI_icon_edit-ltr-progressive.svg.png 1.5x, //upload.wikimedia.org/wikipedia/en/thumb/8/8a/OOjs_UI_icon_edit-ltr-progressive.svg/20px-OOjs_UI_icon_edit-ltr-progressive.svg.png 2x\" style=\"vertical-align: text-top\" width=\"10\"/></a></div></th></tr><tr><th class=\"navbox-group\" scope=\"row\" style=\"width:1%\">General</th><td class=\"navbox-list-with-group navbox-list navbox-odd\" style=\"width:100%;padding:0\"><div style=\"padding:0 0.25em\">\n<ul><li><a class=\"mw-redirect\" href=\"/wiki/ISNI_(identifier)\" title=\"ISNI (identifier)\">ISNI</a>\n<ul><li><span class=\"uid\"><a class=\"external text\" href=\"https://isni.org/isni/0000000117676961\" rel=\"nofollow\">1</a></span></li></ul></li>\n<li><a class=\"mw-redirect\" href=\"/wiki/VIAF_(identifier)\" title=\"VIAF (identifier)\">VIAF</a>\n<ul><li><span class=\"uid\"><a class=\"external text\" href=\"https://viaf.org/viaf/65990747\" rel=\"nofollow\">1</a></span></li></ul></li>\n<li><span class=\"uid\"><a class=\"external text\" href=\"https://www.worldcat.org/identities/lccn-nb2005019157/\" rel=\"nofollow\">WorldCat</a></span></li></ul>\n</div></td></tr><tr><th class=\"navbox-group\" scope=\"row\" style=\"width:1%\">National libraries</th><td class=\"navbox-list-with-group navbox-list navbox-even\" style=\"width:100%;padding:0\"><div style=\"padding:0 0.25em\">\n<ul><li><span class=\"uid\"><a class=\"external text\" href=\"https://catalogue.bnf.fr/ark:/12148/cb16051223g\" rel=\"nofollow\">France</a> <a class=\"external text\" href=\"https://data.bnf.fr/ark:/12148/cb16051223g\" rel=\"nofollow\">(data)</a></span></li>\n<li><span class=\"uid\"><a class=\"external text\" href=\"http://uli.nli.org.il/F/?func=find-b&amp;local_base=NLX10&amp;find_code=UID&amp;request=987007429197205171\" rel=\"nofollow\">Israel</a></span></li>\n<li><span class=\"uid\"><a class=\"external text\" href=\"https://id.loc.gov/authorities/names/nb2005019157\" rel=\"nofollow\">United States</a></span></li>\n<li><span class=\"uid\"><a class=\"external text\" href=\"http://data.bibliotheken.nl/id/thes/p323341101\" rel=\"nofollow\">Netherlands</a></span></li></ul>\n</div></td></tr><tr><th class=\"navbox-group\" scope=\"row\" style=\"width:1%\">Other</th><td class=\"navbox-list-with-group navbox-list navbox-odd\" style=\"width:100%;padding:0\"><div style=\"padding:0 0.25em\">\n<ul><li><a class=\"mw-redirect\" href=\"/wiki/SUDOC_(identifier)\" title=\"SUDOC (identifier)\">SUDOC (France)</a>\n<ul><li><span class=\"uid\"><a class=\"external text\" href=\"https://www.idref.fr/125311788\" rel=\"nofollow\">1</a></span></li></ul></li></ul>\n</div></td></tr></tbody></table></div>\n<!-- \nNewPP limit report\nParsed by mw2271\nCached time: 20221116015201\nCache expiry: 1814400\nReduced expiry: false\nComplications: [vary‐revision‐sha1, show‐toc]\nCPU time usage: 0.425 seconds\nReal time usage: 0.594 seconds\nPreprocessor visited node count: 3175/1000000\nPost‐expand include size: 50139/2097152 bytes\nTemplate argument size: 4266/2097152 bytes\nHighest expansion depth: 16/100\nExpensive parser function count: 9/500\nUnstrip recursion depth: 1/20\nUnstrip post‐expand size: 55165/5000000 bytes\nLua time usage: 0.225/10.000 seconds\nLua memory usage: 9698902/52428800 bytes\nNumber of Wikibase entities loaded: 1/400\n-->\n<!--\nTransclusion expansion time report (%,ms,calls,template)\n100.00%  547.017      1 -total\n 28.92%  158.223      1 Template:Infobox_scientist\n 27.59%  150.900      1 Template:Infobox_person\n 27.22%  148.877      1 Template:Reflist\n 26.84%  146.831      2 Template:Infobox\n 16.77%   91.728     12 Template:Cite_web\n 11.90%   65.091      1 Template:Authority_control\n 11.18%   61.168      1 Template:Short_description\n  9.50%   51.950      5 Template:Br_separated_entries\n  8.80%   48.137      1 Template:ISBN\n-->\n<!-- Saved in parser cache with key enwiki:pcache:idhash:1513690-0!canonical and timestamp 20221116015200 and revision id 1077952888.\n -->\n</div><noscript><img alt=\"\" height=\"1\" src=\"//en.wikipedia.org/wiki/Special:CentralAutoLogin/start?type=1x1\" style=\"border: none; position: absolute;\" title=\"\" width=\"1\"/></noscript>\n<div class=\"printfooter\" data-nosnippet=\"\">Retrieved from \"<a dir=\"ltr\" href=\"https://en.wikipedia.org/w/index.php?title=Miguel_Alcubierre&amp;oldid=1077952888\">https://en.wikipedia.org/w/index.php?title=Miguel_Alcubierre&amp;oldid=1077952888</a>\"</div></div>\n<div class=\"catlinks\" data-mw=\"interface\" id=\"catlinks\"><div class=\"mw-normal-catlinks\" id=\"mw-normal-catlinks\"><a href=\"/wiki/Help:Category\" title=\"Help:Category\">Categories</a>: <ul><li><a href=\"/wiki/Category:1964_births\" title=\"Category:1964 births\">1964 births</a></li><li><a href=\"/wiki/Category:Living_people\" title=\"Category:Living people\">Living people</a></li><li><a href=\"/wiki/Category:21st-century_Mexican_physicists\" title=\"Category:21st-century Mexican physicists\">21st-century Mexican physicists</a></li><li><a href=\"/wiki/Category:Mexican_nuclear_physicists\" title=\"Category:Mexican nuclear physicists\">Mexican nuclear physicists</a></li><li><a href=\"/wiki/Category:Scientists_from_Mexico_City\" title=\"Category:Scientists from Mexico City\">Scientists from Mexico City</a></li><li><a href=\"/wiki/Category:National_Autonomous_University_of_Mexico_alumni\" title=\"Category:National Autonomous University of Mexico alumni\">National Autonomous University of Mexico alumni</a></li><li><a href=\"/wiki/Category:National_Autonomous_University_of_Mexico_faculty\" title=\"Category:National Autonomous University of Mexico faculty\">National Autonomous University of Mexico faculty</a></li><li><a href=\"/wiki/Category:Alumni_of_Cardiff_University\" title=\"Category:Alumni of Cardiff University\">Alumni of Cardiff University</a></li><li><a href=\"/wiki/Category:Theoretical_physicists\" title=\"Category:Theoretical physicists\">Theoretical physicists</a></li></ul></div><div class=\"mw-hidden-catlinks mw-hidden-cats-hidden\" id=\"mw-hidden-catlinks\">Hidden categories: <ul><li><a href=\"/wiki/Category:Webarchive_template_wayback_links\" title=\"Category:Webarchive template wayback links\">Webarchive template wayback links</a></li><li><a href=\"/wiki/Category:CS1_Spanish-language_sources_(es)\" title=\"Category:CS1 Spanish-language sources (es)\">CS1 Spanish-language sources (es)</a></li><li><a href=\"/wiki/Category:Articles_with_short_description\" title=\"Category:Articles with short description\">Articles with short description</a></li><li><a href=\"/wiki/Category:Short_description_matches_Wikidata\" title=\"Category:Short description matches Wikidata\">Short description matches Wikidata</a></li><li><a href=\"/wiki/Category:Articles_with_hCards\" title=\"Category:Articles with hCards\">Articles with hCards</a></li><li><a href=\"/wiki/Category:Commons_category_link_is_on_Wikidata\" title=\"Category:Commons category link is on Wikidata\">Commons category link is on Wikidata</a></li><li><a href=\"/wiki/Category:Articles_with_ISNI_identifiers\" title=\"Category:Articles with ISNI identifiers\">Articles with ISNI identifiers</a></li><li><a href=\"/wiki/Category:Articles_with_VIAF_identifiers\" title=\"Category:Articles with VIAF identifiers\">Articles with VIAF identifiers</a></li><li><a href=\"/wiki/Category:Articles_with_WORLDCATID_identifiers\" title=\"Category:Articles with WORLDCATID identifiers\">Articles with WORLDCATID identifiers</a></li><li><a href=\"/wiki/Category:Articles_with_BNF_identifiers\" title=\"Category:Articles with BNF identifiers\">Articles with BNF identifiers</a></li><li><a href=\"/wiki/Category:Articles_with_J9U_identifiers\" title=\"Category:Articles with J9U identifiers\">Articles with J9U identifiers</a></li><li><a href=\"/wiki/Category:Articles_with_LCCN_identifiers\" title=\"Category:Articles with LCCN identifiers\">Articles with LCCN identifiers</a></li><li><a href=\"/wiki/Category:Articles_with_NTA_identifiers\" title=\"Category:Articles with NTA identifiers\">Articles with NTA identifiers</a></li><li><a href=\"/wiki/Category:Articles_with_SUDOC_identifiers\" title=\"Category:Articles with SUDOC identifiers\">Articles with SUDOC identifiers</a></li></ul></div></div>\n</div>\n</div>\n<div id=\"mw-navigation\">\n<h2>Navigation menu</h2>\n<div id=\"mw-head\">\n<nav aria-labelledby=\"p-personal-label\" class=\"vector-menu mw-portlet mw-portlet-personal vector-user-menu-legacy\" id=\"p-personal\" role=\"navigation\">\n<h3 class=\"vector-menu-heading\" id=\"p-personal-label\">\n<span class=\"vector-menu-heading-label\">Personal tools</span>\n</h3>\n<div class=\"vector-menu-content\">\n<ul class=\"vector-menu-content-list\"><li class=\"mw-list-item\" id=\"pt-anonuserpage\"><span title=\"The user page for the IP address you are editing as\">Not logged in</span></li><li class=\"mw-list-item\" id=\"pt-anontalk\"><a accesskey=\"n\" href=\"/wiki/Special:MyTalk\" title=\"Discussion about edits from this IP address [n]\"><span>Talk</span></a></li><li class=\"mw-list-item\" id=\"pt-anoncontribs\"><a accesskey=\"y\" href=\"/wiki/Special:MyContributions\" title=\"A list of edits made from this IP address [y]\"><span>Contributions</span></a></li><li class=\"mw-list-item\" id=\"pt-createaccount\"><a href=\"/w/index.php?title=Special:CreateAccount&amp;returnto=Miguel+Alcubierre\" title=\"You are encouraged to create an account and log in; however, it is not mandatory\"><span>Create account</span></a></li><li class=\"mw-list-item\" id=\"pt-login\"><a accesskey=\"o\" href=\"/w/index.php?title=Special:UserLogin&amp;returnto=Miguel+Alcubierre\" title=\"You're encouraged to log in; however, it's not mandatory. [o]\"><span>Log in</span></a></li></ul>\n</div>\n</nav>\n<div id=\"left-navigation\">\n<nav aria-labelledby=\"p-namespaces-label\" class=\"vector-menu mw-portlet mw-portlet-namespaces vector-menu-tabs vector-menu-tabs-legacy\" id=\"p-namespaces\" role=\"navigation\">\n<h3 class=\"vector-menu-heading\" id=\"p-namespaces-label\">\n<span class=\"vector-menu-heading-label\">Namespaces</span>\n</h3>\n<div class=\"vector-menu-content\">\n<ul class=\"vector-menu-content-list\"><li class=\"selected mw-list-item\" id=\"ca-nstab-main\"><a accesskey=\"c\" href=\"/wiki/Miguel_Alcubierre\" title=\"View the content page [c]\"><span>Article</span></a></li><li class=\"mw-list-item\" id=\"ca-talk\"><a accesskey=\"t\" href=\"/wiki/Talk:Miguel_Alcubierre\" rel=\"discussion\" title=\"Discuss improvements to the content page [t]\"><span>Talk</span></a></li></ul>\n</div>\n</nav>\n<nav aria-labelledby=\"p-variants-label\" class=\"vector-menu mw-portlet mw-portlet-variants emptyPortlet vector-menu-dropdown-noicon vector-menu-dropdown\" id=\"p-variants\" role=\"navigation\">\n<input aria-haspopup=\"true\" aria-labelledby=\"p-variants-label\" class=\"vector-menu-checkbox\" data-event-name=\"ui.dropdown-p-variants\" id=\"p-variants-checkbox\" role=\"button\" type=\"checkbox\"/>\n<label aria-label=\"Change language variant\" class=\"vector-menu-heading\" id=\"p-variants-label\">\n<span class=\"vector-menu-heading-label\">English</span>\n</label>\n<div class=\"vector-menu-content\">\n<ul class=\"vector-menu-content-list\"></ul>\n</div>\n</nav>\n</div>\n<div id=\"right-navigation\">\n<nav aria-labelledby=\"p-views-label\" class=\"vector-menu mw-portlet mw-portlet-views vector-menu-tabs vector-menu-tabs-legacy\" id=\"p-views\" role=\"navigation\">\n<h3 class=\"vector-menu-heading\" id=\"p-views-label\">\n<span class=\"vector-menu-heading-label\">Views</span>\n</h3>\n<div class=\"vector-menu-content\">\n<ul class=\"vector-menu-content-list\"><li class=\"selected mw-list-item\" id=\"ca-view\"><a href=\"/wiki/Miguel_Alcubierre\"><span>Read</span></a></li><li class=\"mw-list-item\" id=\"ca-edit\"><a accesskey=\"e\" href=\"/w/index.php?title=Miguel_Alcubierre&amp;action=edit\" title=\"Edit this page [e]\"><span>Edit</span></a></li><li class=\"mw-list-item\" id=\"ca-history\"><a accesskey=\"h\" href=\"/w/index.php?title=Miguel_Alcubierre&amp;action=history\" title=\"Past revisions of this page [h]\"><span>View history</span></a></li></ul>\n</div>\n</nav>\n<nav aria-labelledby=\"p-cactions-label\" class=\"vector-menu mw-portlet mw-portlet-cactions emptyPortlet vector-menu-dropdown-noicon vector-menu-dropdown\" id=\"p-cactions\" role=\"navigation\" title=\"More options\">\n<input aria-haspopup=\"true\" aria-labelledby=\"p-cactions-label\" class=\"vector-menu-checkbox\" data-event-name=\"ui.dropdown-p-cactions\" id=\"p-cactions-checkbox\" role=\"button\" type=\"checkbox\"/>\n<label class=\"vector-menu-heading\" id=\"p-cactions-label\">\n<span class=\"vector-menu-heading-label\">More</span>\n</label>\n<div class=\"vector-menu-content\">\n<ul class=\"vector-menu-content-list\"></ul>\n</div>\n</nav>\n<div class=\"vector-search-box-vue vector-search-box-show-thumbnail vector-search-box-auto-expand-width vector-search-box\" id=\"p-search\" role=\"search\">\n<div>\n<h3>\n<label for=\"searchInput\">Search</label>\n</h3>\n<form action=\"/w/index.php\" class=\"vector-search-box-form\" id=\"searchform\">\n<div class=\"vector-search-box-inner\" data-search-loc=\"header-navigation\" id=\"simpleSearch\">\n<input accesskey=\"f\" aria-label=\"Search Wikipedia\" autocapitalize=\"sentences\" class=\"vector-search-box-input\" id=\"searchInput\" name=\"search\" placeholder=\"Search Wikipedia\" title=\"Search Wikipedia [f]\" type=\"search\"/>\n<input name=\"title\" type=\"hidden\" value=\"Special:Search\"/>\n<input class=\"searchButton mw-fallbackSearchButton\" id=\"mw-searchButton\" name=\"fulltext\" title=\"Search Wikipedia for this text\" type=\"submit\" value=\"Search\"/>\n<input class=\"searchButton\" id=\"searchButton\" name=\"go\" title=\"Go to a page with this exact name if it exists\" type=\"submit\" value=\"Go\"/>\n</div>\n</form>\n</div>\n</div>\n</div>\n</div>\n<div id=\"mw-panel\">\n<div id=\"p-logo\" role=\"banner\">\n<a class=\"mw-wiki-logo\" href=\"/wiki/Main_Page\" title=\"Visit the main page\"></a>\n</div>\n<nav aria-labelledby=\"p-navigation-label\" class=\"vector-menu mw-portlet mw-portlet-navigation vector-menu-portal portal\" id=\"p-navigation\" role=\"navigation\">\n<h3 class=\"vector-menu-heading\" id=\"p-navigation-label\">\n<span class=\"vector-menu-heading-label\">Navigation</span>\n</h3>\n<div class=\"vector-menu-content\">\n<ul class=\"vector-menu-content-list\"><li class=\"mw-list-item\" id=\"n-mainpage-description\"><a accesskey=\"z\" href=\"/wiki/Main_Page\" title=\"Visit the main page [z]\"><span>Main page</span></a></li><li class=\"mw-list-item\" id=\"n-contents\"><a href=\"/wiki/Wikipedia:Contents\" title=\"Guides to browsing Wikipedia\"><span>Contents</span></a></li><li class=\"mw-list-item\" id=\"n-currentevents\"><a href=\"/wiki/Portal:Current_events\" title=\"Articles related to current events\"><span>Current events</span></a></li><li class=\"mw-list-item\" id=\"n-randompage\"><a accesskey=\"x\" href=\"/wiki/Special:Random\" title=\"Visit a randomly selected article [x]\"><span>Random article</span></a></li><li class=\"mw-list-item\" id=\"n-aboutsite\"><a href=\"/wiki/Wikipedia:About\" title=\"Learn about Wikipedia and how it works\"><span>About Wikipedia</span></a></li><li class=\"mw-list-item\" id=\"n-contactpage\"><a href=\"//en.wikipedia.org/wiki/Wikipedia:Contact_us\" title=\"How to contact Wikipedia\"><span>Contact us</span></a></li><li class=\"mw-list-item\" id=\"n-sitesupport\"><a href=\"https://donate.wikimedia.org/wiki/Special:FundraiserRedirector?utm_source=donate&amp;utm_medium=sidebar&amp;utm_campaign=C13_en.wikipedia.org&amp;uselang=en\" title=\"Support us by donating to the Wikimedia Foundation\"><span>Donate</span></a></li></ul>\n</div>\n</nav>\n<nav aria-labelledby=\"p-interaction-label\" class=\"vector-menu mw-portlet mw-portlet-interaction vector-menu-portal portal\" id=\"p-interaction\" role=\"navigation\">\n<h3 class=\"vector-menu-heading\" id=\"p-interaction-label\">\n<span class=\"vector-menu-heading-label\">Contribute</span>\n</h3>\n<div class=\"vector-menu-content\">\n<ul class=\"vector-menu-content-list\"><li class=\"mw-list-item\" id=\"n-help\"><a href=\"/wiki/Help:Contents\" title=\"Guidance on how to use and edit Wikipedia\"><span>Help</span></a></li><li class=\"mw-list-item\" id=\"n-introduction\"><a href=\"/wiki/Help:Introduction\" title=\"Learn how to edit Wikipedia\"><span>Learn to edit</span></a></li><li class=\"mw-list-item\" id=\"n-portal\"><a href=\"/wiki/Wikipedia:Community_portal\" title=\"The hub for editors\"><span>Community portal</span></a></li><li class=\"mw-list-item\" id=\"n-recentchanges\"><a accesskey=\"r\" href=\"/wiki/Special:RecentChanges\" title=\"A list of recent changes to Wikipedia [r]\"><span>Recent changes</span></a></li><li class=\"mw-list-item\" id=\"n-upload\"><a href=\"/wiki/Wikipedia:File_Upload_Wizard\" title=\"Add images or other media for use on Wikipedia\"><span>Upload file</span></a></li></ul>\n</div>\n</nav>\n<nav aria-labelledby=\"p-tb-label\" class=\"vector-menu mw-portlet mw-portlet-tb vector-menu-portal portal\" id=\"p-tb\" role=\"navigation\">\n<h3 class=\"vector-menu-heading\" id=\"p-tb-label\">\n<span class=\"vector-menu-heading-label\">Tools</span>\n</h3>\n<div class=\"vector-menu-content\">\n<ul class=\"vector-menu-content-list\"><li class=\"mw-list-item\" id=\"t-whatlinkshere\"><a accesskey=\"j\" href=\"/wiki/Special:WhatLinksHere/Miguel_Alcubierre\" title=\"List of all English Wikipedia pages containing links to this page [j]\"><span>What links here</span></a></li><li class=\"mw-list-item\" id=\"t-recentchangeslinked\"><a accesskey=\"k\" href=\"/wiki/Special:RecentChangesLinked/Miguel_Alcubierre\" rel=\"nofollow\" title=\"Recent changes in pages linked from this page [k]\"><span>Related changes</span></a></li><li class=\"mw-list-item\" id=\"t-upload\"><a accesskey=\"u\" href=\"/wiki/Wikipedia:File_Upload_Wizard\" title=\"Upload files [u]\"><span>Upload file</span></a></li><li class=\"mw-list-item\" id=\"t-specialpages\"><a accesskey=\"q\" href=\"/wiki/Special:SpecialPages\" title=\"A list of all special pages [q]\"><span>Special pages</span></a></li><li class=\"mw-list-item\" id=\"t-permalink\"><a href=\"/w/index.php?title=Miguel_Alcubierre&amp;oldid=1077952888\" title=\"Permanent link to this revision of this page\"><span>Permanent link</span></a></li><li class=\"mw-list-item\" id=\"t-info\"><a href=\"/w/index.php?title=Miguel_Alcubierre&amp;action=info\" title=\"More information about this page\"><span>Page information</span></a></li><li class=\"mw-list-item\" id=\"t-cite\"><a href=\"/w/index.php?title=Special:CiteThisPage&amp;page=Miguel_Alcubierre&amp;id=1077952888&amp;wpFormIdentifier=titleform\" title=\"Information on how to cite this page\"><span>Cite this page</span></a></li><li class=\"mw-list-item\" id=\"t-wikibase\"><a accesskey=\"g\" href=\"https://www.wikidata.org/wiki/Special:EntityPage/Q2056796\" title=\"Structured data on this page hosted by Wikidata [g]\"><span>Wikidata item</span></a></li></ul>\n</div>\n</nav>\n<nav aria-labelledby=\"p-coll-print_export-label\" class=\"vector-menu mw-portlet mw-portlet-coll-print_export vector-menu-portal portal\" id=\"p-coll-print_export\" role=\"navigation\">\n<h3 class=\"vector-menu-heading\" id=\"p-coll-print_export-label\">\n<span class=\"vector-menu-heading-label\">Print/export</span>\n</h3>\n<div class=\"vector-menu-content\">\n<ul class=\"vector-menu-content-list\"><li class=\"mw-list-item\" id=\"coll-download-as-rl\"><a href=\"/w/index.php?title=Special:DownloadAsPdf&amp;page=Miguel_Alcubierre&amp;action=show-download-screen\" title=\"Download this page as a PDF file\"><span>Download as PDF</span></a></li><li class=\"mw-list-item\" id=\"t-print\"><a accesskey=\"p\" href=\"/w/index.php?title=Miguel_Alcubierre&amp;printable=yes\" title=\"Printable version of this page [p]\"><span>Printable version</span></a></li></ul>\n</div>\n</nav>\n<nav aria-labelledby=\"p-wikibase-otherprojects-label\" class=\"vector-menu mw-portlet mw-portlet-wikibase-otherprojects vector-menu-portal portal\" id=\"p-wikibase-otherprojects\" role=\"navigation\">\n<h3 class=\"vector-menu-heading\" id=\"p-wikibase-otherprojects-label\">\n<span class=\"vector-menu-heading-label\">In other projects</span>\n</h3>\n<div class=\"vector-menu-content\">\n<ul class=\"vector-menu-content-list\"><li class=\"wb-otherproject-link wb-otherproject-commons mw-list-item\"><a href=\"https://commons.wikimedia.org/wiki/Category:Miguel_Alcubierre\" hreflang=\"en\"><span>Wikimedia Commons</span></a></li></ul>\n</div>\n</nav>\n<nav aria-labelledby=\"p-lang-label\" class=\"vector-menu mw-portlet mw-portlet-lang vector-menu-portal portal\" id=\"p-lang\" role=\"navigation\">\n<h3 class=\"vector-menu-heading\" id=\"p-lang-label\">\n<span class=\"vector-menu-heading-label\">Languages</span>\n</h3>\n<div class=\"vector-menu-content\">\n<ul class=\"vector-menu-content-list\"><li class=\"interlanguage-link interwiki-ar mw-list-item\"><a class=\"interlanguage-link-target\" href=\"https://ar.wikipedia.org/wiki/%D9%85%D9%8A%D8%AC%D9%8A%D9%84_%D8%A3%D9%84%D9%83%D9%88%D8%A8%D9%8A%D9%8A%D8%B1\" hreflang=\"ar\" lang=\"ar\" title=\"ميجيل ألكوبيير – Arabic\"><span>العربية</span></a></li><li class=\"interlanguage-link interwiki-an mw-list-item\"><a class=\"interlanguage-link-target\" href=\"https://an.wikipedia.org/wiki/Miguel_Alcubierre\" hreflang=\"an\" lang=\"an\" title=\"Miguel Alcubierre – Aragonese\"><span>Aragonés</span></a></li><li class=\"interlanguage-link interwiki-azb mw-list-item\"><a class=\"interlanguage-link-target\" href=\"https://azb.wikipedia.org/wiki/%D9%85%DB%8C%D9%82%D9%84_%D8%A2%D9%84%D9%88%D8%A8%DB%8C%D8%B1%D9%87\" hreflang=\"azb\" lang=\"azb\" title=\"میقل آلوبیره – South Azerbaijani\"><span>تۆرکجه</span></a></li><li class=\"interlanguage-link interwiki-bn mw-list-item\"><a class=\"interlanguage-link-target\" href=\"https://bn.wikipedia.org/wiki/%E0%A6%AE%E0%A6%BF%E0%A6%97%E0%A7%87%E0%A6%B2_%E0%A6%86%E0%A6%B2%E0%A6%95%E0%A7%81%E0%A6%AC%E0%A6%BF%E0%A6%AF%E0%A6%BC%E0%A7%87%E0%A6%B0%E0%A7%87\" hreflang=\"bn\" lang=\"bn\" title=\"মিগেল আলকুবিয়েরে – Bangla\"><span>বাংলা</span></a></li><li class=\"interlanguage-link interwiki-ca mw-list-item\"><a class=\"interlanguage-link-target\" href=\"https://ca.wikipedia.org/wiki/Miguel_Alcubierre\" hreflang=\"ca\" lang=\"ca\" title=\"Miguel Alcubierre – Catalan\"><span>Català</span></a></li><li class=\"interlanguage-link interwiki-es mw-list-item\"><a class=\"interlanguage-link-target\" href=\"https://es.wikipedia.org/wiki/Miguel_Alcubierre\" hreflang=\"es\" lang=\"es\" title=\"Miguel Alcubierre – Spanish\"><span>Español</span></a></li><li class=\"interlanguage-link interwiki-fa mw-list-item\"><a class=\"interlanguage-link-target\" href=\"https://fa.wikipedia.org/wiki/%D9%85%DB%8C%DA%AF%D9%84_%D8%A2%D9%84%D9%88%D8%A8%DB%8C%D8%B1%D9%87\" hreflang=\"fa\" lang=\"fa\" title=\"میگل آلوبیره – Persian\"><span>فارسی</span></a></li><li class=\"interlanguage-link interwiki-fr mw-list-item\"><a class=\"interlanguage-link-target\" href=\"https://fr.wikipedia.org/wiki/Miguel_Alcubierre\" hreflang=\"fr\" lang=\"fr\" title=\"Miguel Alcubierre – French\"><span>Français</span></a></li><li class=\"interlanguage-link interwiki-ko mw-list-item\"><a class=\"interlanguage-link-target\" href=\"https://ko.wikipedia.org/wiki/%EB%AF%B8%EA%B2%94_%EC%95%8C%EC%BF%A0%EB%B9%84%EC%97%90%EB%A0%88\" hreflang=\"ko\" lang=\"ko\" title=\"미겔 알쿠비에레 – Korean\"><span>한국어</span></a></li><li class=\"interlanguage-link interwiki-io mw-list-item\"><a class=\"interlanguage-link-target\" href=\"https://io.wikipedia.org/wiki/Miguel_Alcubierre\" hreflang=\"io\" lang=\"io\" title=\"Miguel Alcubierre – Ido\"><span>Ido</span></a></li><li class=\"interlanguage-link interwiki-id mw-list-item\"><a class=\"interlanguage-link-target\" href=\"https://id.wikipedia.org/wiki/Miguel_Alcubierre\" hreflang=\"id\" lang=\"id\" title=\"Miguel Alcubierre – Indonesian\"><span>Bahasa Indonesia</span></a></li><li class=\"interlanguage-link interwiki-it mw-list-item\"><a class=\"interlanguage-link-target\" href=\"https://it.wikipedia.org/wiki/Miguel_Alcubierre\" hreflang=\"it\" lang=\"it\" title=\"Miguel Alcubierre – Italian\"><span>Italiano</span></a></li><li class=\"interlanguage-link interwiki-he mw-list-item\"><a class=\"interlanguage-link-target\" href=\"https://he.wikipedia.org/wiki/%D7%9E%D7%99%D7%92%D7%9C_%D7%90%D7%9C%D7%A7%D7%95%D7%91%D7%99%D7%99%D7%A8%D7%94\" hreflang=\"he\" lang=\"he\" title=\"מיגל אלקוביירה – Hebrew\"><span>עברית</span></a></li><li class=\"interlanguage-link interwiki-lv mw-list-item\"><a class=\"interlanguage-link-target\" href=\"https://lv.wikipedia.org/wiki/Migels_Alkubjerre\" hreflang=\"lv\" lang=\"lv\" title=\"Migels Alkubjerre – Latvian\"><span>Latviešu</span></a></li><li class=\"interlanguage-link interwiki-arz mw-list-item\"><a class=\"interlanguage-link-target\" href=\"https://arz.wikipedia.org/wiki/%D9%85%D9%8A%D8%AC%D9%8A%D9%84_%D8%A7%D9%84%D9%83%D9%88%D8%A8%D9%8A%D9%8A%D8%B1\" hreflang=\"arz\" lang=\"arz\" title=\"ميجيل الكوبيير – Egyptian Arabic\"><span>مصرى</span></a></li><li class=\"interlanguage-link interwiki-nl mw-list-item\"><a class=\"interlanguage-link-target\" href=\"https://nl.wikipedia.org/wiki/Miguel_Alcubierre\" hreflang=\"nl\" lang=\"nl\" title=\"Miguel Alcubierre – Dutch\"><span>Nederlands</span></a></li><li class=\"interlanguage-link interwiki-pt mw-list-item\"><a class=\"interlanguage-link-target\" href=\"https://pt.wikipedia.org/wiki/Miguel_Alcubierre\" hreflang=\"pt\" lang=\"pt\" title=\"Miguel Alcubierre – Portuguese\"><span>Português</span></a></li><li class=\"interlanguage-link interwiki-ru mw-list-item\"><a class=\"interlanguage-link-target\" href=\"https://ru.wikipedia.org/wiki/%D0%90%D0%BB%D1%8C%D0%BA%D1%83%D0%B1%D1%8C%D0%B5%D1%80%D1%80%D0%B5,_%D0%9C%D0%B8%D0%B3%D0%B5%D0%BB%D1%8C\" hreflang=\"ru\" lang=\"ru\" title=\"Алькубьерре, Мигель – Russian\"><span>Русский</span></a></li><li class=\"interlanguage-link interwiki-sv mw-list-item\"><a class=\"interlanguage-link-target\" href=\"https://sv.wikipedia.org/wiki/Miguel_Alcubierre\" hreflang=\"sv\" lang=\"sv\" title=\"Miguel Alcubierre – Swedish\"><span>Svenska</span></a></li><li class=\"interlanguage-link interwiki-tr mw-list-item\"><a class=\"interlanguage-link-target\" href=\"https://tr.wikipedia.org/wiki/Miguel_Alcubierre\" hreflang=\"tr\" lang=\"tr\" title=\"Miguel Alcubierre – Turkish\"><span>Türkçe</span></a></li><li class=\"interlanguage-link interwiki-uk mw-list-item\"><a class=\"interlanguage-link-target\" href=\"https://uk.wikipedia.org/wiki/%D0%9C%D1%96%D0%B3%D0%B5%D0%BB%D1%8C_%D0%90%D0%BB%D1%8C%D0%BA%D1%83%D0%B1%27%D1%94%D1%80%D1%80%D0%B5\" hreflang=\"uk\" lang=\"uk\" title=\"Мігель Алькуб'єрре – Ukrainian\"><span>Українська</span></a></li><li class=\"interlanguage-link interwiki-zh mw-list-item\"><a class=\"interlanguage-link-target\" href=\"https://zh.wikipedia.org/wiki/%E7%B1%B3%E7%B5%A6%E7%88%BE%C2%B7%E9%98%BF%E5%BA%AB%E5%88%A5%E7%91%9E\" hreflang=\"zh\" lang=\"zh\" title=\"米給爾·阿庫別瑞 – Chinese\"><span>中文</span></a></li></ul>\n<div class=\"after-portlet after-portlet-lang\"><span class=\"wb-langlinks-edit wb-langlinks-link\"><a class=\"wbc-editpage\" href=\"https://www.wikidata.org/wiki/Special:EntityPage/Q2056796#sitelinks-wikipedia\" title=\"Edit interlanguage links\">Edit links</a></span></div>\n</div>\n</nav>\n</div>\n</div>\n<footer class=\"mw-footer\" id=\"footer\" role=\"contentinfo\">\n<ul id=\"footer-info\">\n<li id=\"footer-info-lastmod\"> This page was last edited on 19 March 2022, at 03:01<span class=\"anonymous-show\"> (UTC)</span>.</li>\n<li id=\"footer-info-copyright\">Text is available under the <a href=\"//en.wikipedia.org/wiki/Wikipedia:Text_of_Creative_Commons_Attribution-ShareAlike_3.0_Unported_License\" rel=\"license\">Creative Commons Attribution-ShareAlike License 3.0</a><a href=\"//creativecommons.org/licenses/by-sa/3.0/\" rel=\"license\" style=\"display:none;\"></a>;\nadditional terms may apply.  By using this site, you agree to the <a href=\"//foundation.wikimedia.org/wiki/Terms_of_Use\">Terms of Use</a> and <a href=\"//foundation.wikimedia.org/wiki/Privacy_policy\">Privacy Policy</a>. Wikipedia® is a registered trademark of the <a href=\"//www.wikimediafoundation.org/\">Wikimedia Foundation, Inc.</a>, a non-profit organization.</li>\n</ul>\n<ul id=\"footer-places\">\n<li id=\"footer-places-privacy\"><a href=\"https://foundation.wikimedia.org/wiki/Privacy_policy\">Privacy policy</a></li>\n<li id=\"footer-places-about\"><a href=\"/wiki/Wikipedia:About\">About Wikipedia</a></li>\n<li id=\"footer-places-disclaimers\"><a href=\"/wiki/Wikipedia:General_disclaimer\">Disclaimers</a></li>\n<li id=\"footer-places-contact\"><a href=\"//en.wikipedia.org/wiki/Wikipedia:Contact_us\">Contact Wikipedia</a></li>\n<li id=\"footer-places-mobileview\"><a class=\"noprint stopMobileRedirectToggle\" href=\"//en.m.wikipedia.org/w/index.php?title=Miguel_Alcubierre&amp;mobileaction=toggle_view_mobile\">Mobile view</a></li>\n<li id=\"footer-places-developers\"><a href=\"https://developer.wikimedia.org\">Developers</a></li>\n<li id=\"footer-places-statslink\"><a href=\"https://stats.wikimedia.org/#/en.wikipedia.org\">Statistics</a></li>\n<li id=\"footer-places-cookiestatement\"><a href=\"https://foundation.wikimedia.org/wiki/Cookie_statement\">Cookie statement</a></li>\n</ul>\n<ul class=\"noprint\" id=\"footer-icons\">\n<li id=\"footer-copyrightico\"><a href=\"https://wikimediafoundation.org/\"><img alt=\"Wikimedia Foundation\" height=\"31\" loading=\"lazy\" src=\"/static/images/footer/wikimedia-button.png\" srcset=\"/static/images/footer/wikimedia-button-1.5x.png 1.5x, /static/images/footer/wikimedia-button-2x.png 2x\" width=\"88\"/></a></li>\n<li id=\"footer-poweredbyico\"><a href=\"https://www.mediawiki.org/\"><img alt=\"Powered by MediaWiki\" height=\"31\" loading=\"lazy\" src=\"/static/images/footer/poweredby_mediawiki_88x31.png\" srcset=\"/static/images/footer/poweredby_mediawiki_132x47.png 1.5x, /static/images/footer/poweredby_mediawiki_176x62.png 2x\" width=\"88\"/></a></li>\n</ul>\n</footer>\n<script>(RLQ=window.RLQ||[]).push(function(){mw.config.set({\"wgPageParseReport\":{\"limitreport\":{\"cputime\":\"0.425\",\"walltime\":\"0.594\",\"ppvisitednodes\":{\"value\":3175,\"limit\":1000000},\"postexpandincludesize\":{\"value\":50139,\"limit\":2097152},\"templateargumentsize\":{\"value\":4266,\"limit\":2097152},\"expansiondepth\":{\"value\":16,\"limit\":100},\"expensivefunctioncount\":{\"value\":9,\"limit\":500},\"unstrip-depth\":{\"value\":1,\"limit\":20},\"unstrip-size\":{\"value\":55165,\"limit\":5000000},\"entityaccesscount\":{\"value\":1,\"limit\":400},\"timingprofile\":[\"100.00%  547.017      1 -total\",\" 28.92%  158.223      1 Template:Infobox_scientist\",\" 27.59%  150.900      1 Template:Infobox_person\",\" 27.22%  148.877      1 Template:Reflist\",\" 26.84%  146.831      2 Template:Infobox\",\" 16.77%   91.728     12 Template:Cite_web\",\" 11.90%   65.091      1 Template:Authority_control\",\" 11.18%   61.168      1 Template:Short_description\",\"  9.50%   51.950      5 Template:Br_separated_entries\",\"  8.80%   48.137      1 Template:ISBN\"]},\"scribunto\":{\"limitreport-timeusage\":{\"value\":\"0.225\",\"limit\":\"10.000\"},\"limitreport-memusage\":{\"value\":9698902,\"limit\":52428800}},\"cachereport\":{\"origin\":\"mw2271\",\"timestamp\":\"20221116015201\",\"ttl\":1814400,\"transientcontent\":false}}});});</script>\n<script type=\"application/ld+json\">{\"@context\":\"https:\\/\\/schema.org\",\"@type\":\"Article\",\"name\":\"Miguel Alcubierre\",\"url\":\"https:\\/\\/en.wikipedia.org\\/wiki\\/Miguel_Alcubierre\",\"sameAs\":\"http:\\/\\/www.wikidata.org\\/entity\\/Q2056796\",\"mainEntity\":\"http:\\/\\/www.wikidata.org\\/entity\\/Q2056796\",\"author\":{\"@type\":\"Organization\",\"name\":\"Contributors to Wikimedia projects\"},\"publisher\":{\"@type\":\"Organization\",\"name\":\"Wikimedia Foundation, Inc.\",\"logo\":{\"@type\":\"ImageObject\",\"url\":\"https:\\/\\/www.wikimedia.org\\/static\\/images\\/wmf-hor-googpub.png\"}},\"datePublished\":\"2005-02-16T16:42:55Z\",\"dateModified\":\"2022-03-19T03:01:45Z\",\"image\":\"https:\\/\\/upload.wikimedia.org\\/wikipedia\\/commons\\/f\\/f8\\/Miguel_Alcubierre%E2%80%A201.jpg\",\"headline\":\"Mexican theoretical physicist (born 1964)\"}</script><script type=\"application/ld+json\">{\"@context\":\"https:\\/\\/schema.org\",\"@type\":\"Article\",\"name\":\"Miguel Alcubierre\",\"url\":\"https:\\/\\/en.wikipedia.org\\/wiki\\/Miguel_Alcubierre\",\"sameAs\":\"http:\\/\\/www.wikidata.org\\/entity\\/Q2056796\",\"mainEntity\":\"http:\\/\\/www.wikidata.org\\/entity\\/Q2056796\",\"author\":{\"@type\":\"Organization\",\"name\":\"Contributors to Wikimedia projects\"},\"publisher\":{\"@type\":\"Organization\",\"name\":\"Wikimedia Foundation, Inc.\",\"logo\":{\"@type\":\"ImageObject\",\"url\":\"https:\\/\\/www.wikimedia.org\\/static\\/images\\/wmf-hor-googpub.png\"}},\"datePublished\":\"2005-02-16T16:42:55Z\",\"dateModified\":\"2022-03-19T03:01:45Z\",\"image\":\"https:\\/\\/upload.wikimedia.org\\/wikipedia\\/commons\\/f\\/f8\\/Miguel_Alcubierre%E2%80%A201.jpg\",\"headline\":\"Mexican theoretical physicist (born 1964)\"}</script>\n<script>(RLQ=window.RLQ||[]).push(function(){mw.config.set({\"wgBackendResponseTime\":709,\"wgHostname\":\"mw2271\"});});</script>\n</body>\n</html>",
    "table_of_contents": [
        "1 Personal life",
        "2 Academic life",
        "3 May 1994 paper",
        "4 Media appearances",
        "5 Textbook",
        "6 References"
    ],
    "graphics": [],
    "paragraphs": [
        {
            "title": "",
            "text": "Miguel Alcubierre Moya (born March 28, 1964) is a Mexican theoretical physicist.[4]\nAlcubierre is known for the proposed Alcubierre drive, a speculative warp drive by which a spacecraft could achieve faster-than-light travel.\n\n"
        },
        {
            "title": "Personal life",
            "text": "Alcubierre was born in Mexico City. His father, Miguel Alcubierre Ortiz, a Spanish refugee, arrived in Mexico shortly after the Spanish civil war with his own father, Miguel Alcubierre Pérez.[5] Alcubierre has three younger siblings, among them is historian Beatriz Alcubierre Moya.[6]\n\nFrom elementary throughout high school, Alcubierre attended Colegio Ciudad de México. At the age of 13, his father bought him a small telescope, and, together with sci-fi shows such as Star Trek, motivated him to pursue a scientific career.[7] At the age of 15, after having read Patrick Moore and David Hardy's Challenge of the Stars, Alcubierre decided that he wanted to become an astronomer. He knew that in order to achieve this he would have to study physics first.[8]\n\n"
        },
        {
            "title": "Academic life",
            "text": "Alcubierre obtained a Licentiate degree in physics in 1988 and a MSc degree in theoretical physics in 1990, both at the National Autonomous University of Mexico (UNAM). At the end of 1990, Alcubierre moved to Wales to attend graduate school at Cardiff University, receiving his PhD degree in 1994 through study of numerical general relativity.[4][9][10][11]\nAfter 1996 he worked at the Max Planck Institute for Gravitational Physics in Potsdam, Germany, developing new numerical techniques used in the description of black holes.  Since 2002, he has worked at the Nuclear Sciences Institute of UNAM, where he conducts research in numerical relativity, employing computers to formulate and solve the physical equations first proposed by Albert Einstein.[12] \nThe solitary wave solutions proposed  by Alcubierre for the Einsteinian field equations may possibly  prove general relativity consistent with the experimentally verified non-locality of quantum mechanics. This work militates against the idea that quantum non-locality would ultimately require abandoning the mathematical structure of general relativity.\n\nOn June 11, 2012, Alcubierre was appointed Director of the Nuclear Sciences Institute at UNAM.\n\nOn June 14, 2016, the Governing Board of UNAM re-elected Alcubierre as Director of the Nuclear Sciences Institute for another four-year period.\n\n"
        },
        {
            "title": "May 1994 paper",
            "text": "Alcubierre is best known for the proposal of \"The Warp Drive: Hyper-fast travel within general relativity\" that was published in the science journal Classical and Quantum Gravity.[13]  In this, he describes the Alcubierre drive, a theoretical means of traveling faster than light that does not violate the physical principle that nothing can locally travel faster than light. In this paper,  he constructed a model that might transport a volume of flat space inside a \"bubble\" of curved space. This bubble, named as Hyper-relativistic local-dynamic space, is driven forward by a local expansion of space-time behind it, and an opposite contraction in front of it, so that theoretically a spaceship would be placed in motion by forces generated in the change made by space-time.\n\n"
        },
        {
            "title": "Media appearances",
            "text": "Miguel Alcubierre made a special appearance on the TV productions How William Shatner Changed the World[14]\nand Michio Kaku's Sci Fi Science: Physics of the Impossible,[15][16]\nin which his warp bubble theory was discussed.\n\nAlcubierre has been invited twice to interviews on radio station Radio Educación XEEP (1060 AM), first on February 18, 2011, and later on March 4th 2011, on the technology-related talk show Interfase, where he explained his views on the current state of scientific and technology research in Mexico, and gave a brief introduction to his warp drive model and how it came to be.[17][18]\n\n"
        },
        {
            "title": "Textbook",
            "text": "Introduction to 3+1 Numerical Relativity (International Series of Monographs on Physics, Paperback, 2012, ISBN 978-0199656158)\n\n"
        }
    ],
    "links": [
        "https://en.wikipedia.org/wiki/Spanish_name",
        "https://en.wikipedia.org/wiki/Surname",
        "https://en.wikipedia.org/wiki/Mexico_City",
        "https://en.wikipedia.org/wiki/National_Autonomous_University_of_Mexico",
        "https://en.wikipedia.org/wiki/Cardiff_University",
        "https://en.wikipedia.org/wiki/Alcubierre_drive",
        "https://en.wikipedia.org/wiki/Gabino_Barreda",
        "https://en.wikipedia.org/wiki/Max_Planck_Institute_for_Gravitational_Physics",
        "https://en.wikipedia.org/wiki/National_Autonomous_University_of_Mexico",
        "https://en.wikipedia.org/wiki/Thesis",
        "https://en.wikipedia.org/wiki/Doctoral_advisor",
        "https://en.wikipedia.org/wiki/Theoretical_physicist",
        "https://en.wikipedia.org/wiki/Alcubierre_drive",
        "https://en.wikipedia.org/wiki/Warp_drive",
        "https://en.wikipedia.org/wiki/Spanish_Civil_War",
        "https://en.wikipedia.org/wiki/Science_fiction",
        "https://en.wikipedia.org/wiki/Star_Trek",
        "https://en.wikipedia.org/wiki/Patrick_Moore",
        "https://en.wikipedia.org/wiki/Physics",
        "https://en.wikipedia.org/wiki/Physics",
        "https://en.wikipedia.org/wiki/Master_of_Science",
        "https://en.wikipedia.org/wiki/Theoretical_physics",
        "https://en.wikipedia.org/wiki/National_Autonomous_University_of_Mexico",
        "https://en.wikipedia.org/wiki/Cardiff_University",
        "https://en.wikipedia.org/wiki/Doctor_of_Philosophy",
        "https://en.wikipedia.org/wiki/Numerical_relativity",
        "https://en.wikipedia.org/wiki/Max_Planck_Institute_for_Gravitational_Physics",
        "https://en.wikipedia.org/wiki/Potsdam",
        "https://en.wikipedia.org/wiki/Black_hole",
        "https://en.wikipedia.org/wiki/Soliton",
        "https://en.wikipedia.org/wiki/Einstein_field_equations",
        "https://en.wikipedia.org/wiki/Locality_principle",
        "https://en.wikipedia.org/wiki/Quantum_mechanics",
        "https://en.wikipedia.org/wiki/General_relativity",
        "https://en.wikipedia.org/wiki/Alcubierre_drive",
        "https://en.wikipedia.org/wiki/Spacecraft",
        "https://en.wikipedia.org/wiki/How_William_Shatner_Changed_the_World",
        "https://en.wikipedia.org/wiki/Michio_Kaku",
        "https://en.wikipedia.org/wiki/Analog_Science_Fiction_and_Fact",
        "https://en.wikipedia.org/wiki/Penny_Publications",
        "https://en.wikipedia.org/wiki/YouTube",
        "https://en.wikipedia.org/wiki/Wayback_Machine",
        "https://en.wikipedia.org/wiki/Blog",
        "https://en.wikipedia.org/wiki/Internet_Movie_Database",
        "https://en.wikipedia.org/wiki/Miguel_Alcubierre",
        "https://en.wikipedia.org/wiki/Miguel_Alcubierre",
        "https://en.wikipedia.org/wiki/Main_Page",
        "https://en.wikipedia.org/wiki/Main_Page"
    ]
}